{
  "kpi": [
    {
      "_id": "63bf8239f03239e002001612",
      "totalProfit": "$212000.00",
      "totalRevenue": "$283000.00",
      "totalExpenses": "$71000.00",
      "monthlyData": [
        {
          "month": "january",
          "revenue": "$15989.64",
          "expenses": "$14231.73",
          "operationalExpenses": "$10340.03",
          "nonOperationalExpenses": "$4891.70"
        },
        {
          "month": "february",
          "revenue": "$15832.77",
          "expenses": "$11677.84",
          "operationalExpenses": "$7006.69",
          "nonOperationalExpenses": "$8661.15"
        },
        {
          "month": "march",
          "revenue": "$16481.27",
          "expenses": "$14664.03",
          "operationalExpenses": "$8797.42",
          "nonOperationalExpenses": "$7866.61"
        },
        {
          "month": "april",
          "revenue": "$18229.38",
          "expenses": "$12336.52",
          "operationalExpenses": "$7401.91",
          "nonOperationalExpenses": "$2934.61"
        },
        {
          "month": "may",
          "revenue": "$17401.79",
          "expenses": "$11160.61",
          "operationalExpenses": "$4296.37",
          "nonOperationalExpenses": "$4864.24"
        },
        {
          "month": "june",
          "revenue": "$18274.03",
          "expenses": "$12311.61",
          "operationalExpenses": "$7386.96",
          "nonOperationalExpenses": "$9924.65"
        },
        {
          "month": "july",
          "revenue": "$19349.98",
          "expenses": "$15431.81",
          "operationalExpenses": "$9258.09",
          "nonOperationalExpenses": "$7173.72"
        },
        {
          "month": "august",
          "revenue": "$16647.29",
          "expenses": "$13213.71",
          "operationalExpenses": "$3127.82",
          "nonOperationalExpenses": "$5085.89"
        },
        {
          "month": "september",
          "revenue": "$19344.07",
          "expenses": "$17405.92",
          "operationalExpenses": "$10443.55",
          "nonOperationalExpenses": "$4962.37"
        },
        {
          "month": "october",
          "revenue": "$21160.22",
          "expenses": "$12990.58",
          "operationalExpenses": "$3594.35",
          "nonOperationalExpenses": "$9396.23"
        },
        {
          "month": "november",
          "revenue": "$22655.03",
          "expenses": "$17140.80",
          "operationalExpenses": "$10284.48",
          "nonOperationalExpenses": "$3856.32"
        },
        {
          "month": "december",
          "revenue": "$17757.75",
          "expenses": "$15266.97",
          "operationalExpenses": "$9160.18",
          "nonOperationalExpenses": "$4106.79"
        }
      ],
      "dailyData": [
        { "date": "2022-01-02", "revenue": "$1498.94", "expenses": "$430.64" },
        { "date": "2022-01-03", "revenue": "$935.08", "expenses": "$329.32" },
        { "date": "2022-01-04", "revenue": "$1350.96", "expenses": "$562.49" },
        { "date": "2022-01-05", "revenue": "$1244.33", "expenses": "$679.32" },
        { "date": "2022-01-06", "revenue": "$1132.99", "expenses": "$439.80" },
        { "date": "2022-01-07", "revenue": "$1158.31", "expenses": "$336.12" },
        { "date": "2022-01-08", "revenue": "$1184.66", "expenses": "$516.10" },
        { "date": "2022-01-09", "revenue": "$637.32", "expenses": "$635.06" },
        { "date": "2022-01-10", "revenue": "$1315.21", "expenses": "$560.12" },
        { "date": "2022-01-11", "revenue": "$1093.06", "expenses": "$540.05" },
        { "date": "2022-01-12", "revenue": "$1477.77", "expenses": "$487.16" },
        { "date": "2022-01-13", "revenue": "$1076.09", "expenses": "$616.29" },
        { "date": "2022-01-14", "revenue": "$1130.96", "expenses": "$392.17" },
        { "date": "2022-01-15", "revenue": "$846.42", "expenses": "$548.38" },
        { "date": "2022-01-16", "revenue": "$1182.35", "expenses": "$366.72" },
        { "date": "2022-01-17", "revenue": "$1046.61", "expenses": "$481.56" },
        { "date": "2022-01-18", "revenue": "$601.65", "expenses": "$452.75" },
        { "date": "2022-01-19", "revenue": "$798.33", "expenses": "$351.23" },
        { "date": "2022-01-20", "revenue": "$1499.37", "expenses": "$340.85" },
        { "date": "2022-01-21", "revenue": "$1462.26", "expenses": "$630.31" },
        { "date": "2022-01-22", "revenue": "$1447.38", "expenses": "$476.59" },
        { "date": "2022-01-23", "revenue": "$1194.96", "expenses": "$482.85" },
        { "date": "2022-01-24", "revenue": "$713.11", "expenses": "$754.33" },
        { "date": "2022-01-25", "revenue": "$1084.48", "expenses": "$547.37" },
        { "date": "2022-01-26", "revenue": "$819.53", "expenses": "$653.59" },
        { "date": "2022-01-27", "revenue": "$1306.61", "expenses": "$636.87" },
        { "date": "2022-01-28", "revenue": "$1029.78", "expenses": "$719.46" },
        { "date": "2022-01-29", "revenue": "$1415.18", "expenses": "$387.49" },
        { "date": "2022-01-30", "revenue": "$845.38", "expenses": "$533.93" },
        { "date": "2022-01-31", "revenue": "$764.69", "expenses": "$762.35" },
        { "date": "2022-02-01", "revenue": "$616.49", "expenses": "$658.92" },
        { "date": "2022-02-02", "revenue": "$677.71", "expenses": "$754.69" },
        { "date": "2022-02-03", "revenue": "$1178.84", "expenses": "$491.18" },
        { "date": "2022-02-04", "revenue": "$1024.47", "expenses": "$684.91" },
        { "date": "2022-02-05", "revenue": "$1012.65", "expenses": "$570.41" },
        { "date": "2022-02-06", "revenue": "$1099.22", "expenses": "$689.02" },
        { "date": "2022-02-07", "revenue": "$1425.14", "expenses": "$560.86" },
        { "date": "2022-02-08", "revenue": "$853.77", "expenses": "$617.08" },
        { "date": "2022-02-09", "revenue": "$1269.54", "expenses": "$629.32" },
        { "date": "2022-02-10", "revenue": "$1104.73", "expenses": "$516.93" },
        { "date": "2022-02-11", "revenue": "$1342.17", "expenses": "$643.12" },
        { "date": "2022-02-12", "revenue": "$856.29", "expenses": "$553.88" },
        { "date": "2022-02-13", "revenue": "$1163.82", "expenses": "$521.46" },
        { "date": "2022-02-14", "revenue": "$979.47", "expenses": "$367.22" },
        { "date": "2022-02-15", "revenue": "$1332.15", "expenses": "$681.24" },
        { "date": "2022-02-16", "revenue": "$1014.68", "expenses": "$536.92" },
        { "date": "2022-02-17", "revenue": "$1368.62", "expenses": "$690.27" },
        { "date": "2022-02-18", "revenue": "$848.76", "expenses": "$364.14" },
        { "date": "2022-02-19", "revenue": "$1135.91", "expenses": "$520.18" },
        { "date": "2022-02-20", "revenue": "$1404.29", "expenses": "$532.95" },
        { "date": "2022-02-21", "revenue": "$1417.81", "expenses": "$633.05" },
        { "date": "2022-02-22", "revenue": "$1030.47", "expenses": "$594.77" },
        { "date": "2022-02-23", "revenue": "$1459.12", "expenses": "$536.12" },
        { "date": "2022-02-24", "revenue": "$1392.27", "expenses": "$670.35" },
        { "date": "2022-02-25", "revenue": "$1176.58", "expenses": "$727.65" },
        { "date": "2022-02-26", "revenue": "$976.34", "expenses": "$682.49" },
        { "date": "2022-02-27", "revenue": "$1258.42", "expenses": "$691.03" },
        { "date": "2022-02-28", "revenue": "$1411.23", "expenses": "$722.18" },
        { "date": "2022-03-01", "revenue": "$1153.58", "expenses": "$682.39" },
        { "date": "2022-03-02", "revenue": "$1219.87", "expenses": "$713.12" },
        { "date": "2022-03-03", "revenue": "$1395.64", "expenses": "$603.24" },
        { "date": "2022-03-04", "revenue": "$1056.78", "expenses": "$730.38" },
        { "date": "2022-03-05", "revenue": "$1283.49", "expenses": "$640.27" },
        { "date": "2022-03-06", "revenue": "$1175.21", "expenses": "$546.82" },
        { "date": "2022-03-07", "revenue": "$1246.55", "expenses": "$666.32" },
        { "date": "2022-03-08", "revenue": "$1410.27", "expenses": "$579.93" },
        { "date": "2022-03-09", "revenue": "$1259.83", "expenses": "$504.28" },
        { "date": "2022-03-10", "revenue": "$1032.46", "expenses": "$648.71" },
        { "date": "2022-03-11", "revenue": "$1396.18", "expenses": "$603.91" },
        { "date": "2022-03-12", "revenue": "$1125.68", "expenses": "$718.24" },
        { "date": "2022-03-13", "revenue": "$1189.76", "expenses": "$722.09" },
        { "date": "2022-03-14", "revenue": "$1345.92", "expenses": "$597.12" },
        { "date": "2022-03-15", "revenue": "$1079.43", "expenses": "$693.54" },
        { "date": "2022-03-16", "revenue": "$1384.29", "expenses": "$652.14" },
        { "date": "2022-03-17", "revenue": "$1227.67", "expenses": "$589.24" },
        { "date": "2022-03-18", "revenue": "$1408.92", "expenses": "$675.92" },
        { "date": "2022-03-19", "revenue": "$1283.15", "expenses": "$605.31" },
        { "date": "2022-03-20", "revenue": "$1075.49", "expenses": "$723.34" },
        { "date": "2022-03-21", "revenue": "$1389.72", "expenses": "$619.78" },
        { "date": "2022-03-22", "revenue": "$1176.94", "expenses": "$536.45" },
        { "date": "2022-03-23", "revenue": "$1245.13", "expenses": "$692.17" },
        { "date": "2022-03-24", "revenue": "$1361.88", "expenses": "$702.43" },
        { "date": "2022-03-25", "revenue": "$1167.24", "expenses": "$681.58" },
        { "date": "2022-03-26", "revenue": "$1297.38", "expenses": "$634.19" },
        { "date": "2022-03-27", "revenue": "$1234.71", "expenses": "$547.89" },
        { "date": "2022-03-28", "revenue": "$1422.46", "expenses": "$599.81" },
        { "date": "2022-03-29", "revenue": "$1071.53", "expenses": "$587.46" },
        { "date": "2022-03-30", "revenue": "$1193.92", "expenses": "$708.17" },
        { "date": "2022-03-31", "revenue": "$1378.08", "expenses": "$688.72" }
      ],
      "expensesByCategory": {
        "salaries": "$38000.00",
        "supplies": "$13000.00",
        "services": "$10000.00"
      }
    }
  ],
  "product": 
  [
    {
      "_id": "63bf7ac9f03239e002001600",
      "price": "$43.41",
      "expense": "$5.97",
      "transactions": [
        "63bf7ccef03239554c002449",
        "63bf7ccef03239855d00155c",
        "63bf7ccef032397b4f001603",
        "63bf7ccef03239eb9d0016d4"
      ]
    },
    {
      "_id": "63bf7ac9f03239e002001601",
      "price": "$60.13",
      "expense": "$9.12",
      "transactions": [
        "63bf7ccef032396a8e001696",
        "63bf7ccef0323922d2001694",
        "63bf7ccef03239855d001557",
        "63bf7ccef03239554c00244d"
      ]
    },
    {
      "_id": "63bf7ac9f03239e002001602",
      "price": "$195.05",
      "expense": "$6.72",
      "transactions": [
        "63bf7ccef03239e002001606",
        "63bf7ccef0323922d200169a"
      ]
    },
    {
      "_id": "63bf7ac9f03239e002001603",
      "price": "$46.25",
      "expense": "$9.95",
      "transactions": [
        "63bf7ccef03239aec900155b",
        "63bf7ccef03239eb9d0016d3",
        "63bf7ccef03239aec9001559"
      ]
    },
    {
      "_id": "63bf7ac9f03239e002001604",
      "price": "$87.41",
      "expense": "$7.97",
      "transactions": [
        "63bf7ccef03239855d00155d",
        "63bf7ccef03239855d001561",
        "63bf7ccef03239e00200160e",
        "63bf7ccef0323922d2001697",
        "63bf7ccef032394f5f002442"
      ]
    },
    {
      "_id": "63bf7ac9f03239e002001605",
      "price": "$73.28",
      "expense": "$7.85",
      "transactions": [
        "63bf7ccef03239966c0016a0",
        "63bf7ccef03239966c00169f",
        "63bf7ccef032394cbd0016a0",
        "63bf7ccef03239554c002453",
        "63bf7ccef0323901e6001557"
      ]
    },
    {
      "_id": "63bf7ac9f03239343e00169b",
      "price": "$130.65",
      "expense": "$7.95",
      "transactions": [
        "63bf7ccef0323901e6001560",
        "63bf7ccef032396d89000013"
      ]
    },
    {
      "_id": "63bf7ac9f03239343e00169c",
      "price": "$198.54",
      "expense": "$9.50",
      "transactions": [
        "63bf7ccef03239eb9d0016d9",
        "63bf7ccef032396a8e001696",
        "63bf7ccef03239cf1b0016a7",
        "63bf7ccef0323901e6001562"
      ]
    },
    {
      "_id": "63bf7ac9f03239343e00169d",
      "price": "$147.32",
      "expense": "$5.86",
      "transactions": [
        "63bf7ccef03239343e0016a9",
        "63bf7ccef03239f920001690"
      ]
    },
    {
      "_id": "63bf7ac9f03239343e00169e",
      "price": "$187.22",
      "expense": "$5.82",
      "transactions": [
        "63bf7ccef03239aec9001560",
        "63bf7ccef032396d8900000f",
        "63bf7ccef0323922d2001697"
      ]
    },
    {
      "_id": "63bf7ac9f03239343e00169f",
      "price": "$162.43",
      "expense": "$3.28",
      "transactions": [
        "63bf7ccef032395ccf001697",
        "63bf7ccef0323901e600155e",
        "63bf7ccef03239aec9001559"
      ]
    },
    {
      "_id": "63bf7ac9f03239343e0016a0",
      "price": "$30.09",
      "expense": "$8.55",
      "transactions": [
        "63bf7ccef03239343e0016a3"
      ]
    },
    {
      "_id": "63bf7ac9f0323901e6001551",
      "price": "$31.07",
      "expense": "$4.98",
      "transactions": [
        "63bf7ccef032395ccf001695",
        "63bf7ccef03239eb9d0016dd",
        "63bf7ccef032397b4f001606",
        "63bf7ccef03239855d00155b",
        "63bf7ccef032397b4f001604"
      ]
    },
    {
      "_id": "63bf7ac9f0323901e6001552",
      "price": "$12.21",
      "expense": "$6.82",
      "transactions": [
        "63bf7ccef03239855d00155c",
        "63bf7ccef032395ccf001696",
        "63bf7ccef03239cf1b0016a2",
        "63bf7ccef032396a8e00169a",
        "63bf7ccef03239966c00169a"
      ]
    },
    {
      "_id": "63bf7ac9f0323901e6001553",
      "price": "$76.31",
      "expense": "$3.84",
      "transactions": [
        "63bf7ccef03239e002001608",
        "63bf7ccef0323922d200169b",
        "63bf7ccef03239eb9d0016e6"
      ]
    },
    {
      "_id": "63bf7ac9f0323901e6001554",
      "price": "$169.87",
      "expense": "$8.35",
      "transactions": [
        "63bf7ccef03239eb9d0016d5",
        "63bf7ccef03239966c00169e",
        "63bf7ccef0323974200016a7"
      ]
    },
    {
      "_id": "63bf7ac9f0323901e6001555",
      "price": "$187.36",
      "expense": "$8.12",
      "transactions": [
        "63bf7ccef032394f5f00243a",
        "63bf7ccef03239eb9d0016de",
        "63bf7ccef03239f920001696"
      ]
    },
    {
      "_id": "63bf7ac9f0323901e6001556",
      "price": "$67.29",
      "expense": "$6.32",
      "transactions": [
        "63bf7ccef032396d89000015",
        "63bf7ccef03239f920001690",
        "63bf7ccef03239eb9d0016d2"
      ]
    },
    {
      "_id": "63bf7ac9f032394cbd001699",
      "price": "$85.35",
      "expense": "$9.33",
      "transactions": [
        "63bf7ccef03239aec9001558",
        "63bf7ccef03239f92000169a",
        "63bf7ccef03239742000169d",
        "63bf7ccef03239554c00244a"
      ]
    },
    {
      "_id": "63bf7ac9f032394cbd00169a",
      "price": "$35.75",
      "expense": "$9.93",
      "transactions": [
        "63bf7ccef03239554c002453",
        "63bf7ccef03239e002001608",
        "63bf7ccef0323937a500168d"
      ]
    },
    {
      "_id": "63bf7ac9f032394cbd00169b",
      "price": "$59.80",
      "expense": "$1.51",
      "transactions": [
        "63bf7ccef0323937a5001690",
        "63bf7ccef03239e00200160b",
        "63bf7ccef032394f5f002441",
        "63bf7ccef0323975d60016a3",
        "63bf7ccef032395ccf00169f"
      ]
    },
    {
      "_id": "63bf7ac9f032394cbd00169c",
      "price": "$86.45",
      "expense": "$3.55",
      "transactions": ["63bf7ccef032396d8900000f"]
    },
    {
      "_id": "63bf7ac9f032394cbd00169d",
      "price": "$142.21",
      "expense": "$1.85",
      "transactions": [
        "63bf7ccef032396a8e001698",
        "63bf7ccef03239eb9d0016d0"
      ]
    },
    {
      "_id": "63bf7ac9f032394cbd00169e",
      "price": "$10.01",
      "expense": "$5.61",
      "transactions": [
        "63bf7ccef03239e002001610",
        "63bf7ccef03239f920001699",
        "63bf7ccef03239966c00169a",
        "63bf7ccef03239e002001611",
        "63bf7ccef032394cbd00169f"
      ]
    },
    {
      "_id": "63bf7ac9f03239cf1b001698",
      "price": "$112.78",
      "expense": "$6.74",
      "transactions": ["63bf7ccef032396a8e00169d", "63bf7ccef032396a8e001695"]
    },
    {
      "_id": "63bf7ac9f03239cf1b001699",
      "price": "$156.34",
      "expense": "$6.26",
      "transactions": ["63bf7ccef03239e002001606"]
    },
    {
      "_id": "63bf7ac9f03239cf1b00169a",
      "price": "$119.34",
      "expense": "$8.62",
      "transactions": ["63bf7ccef0323975d600169e", "63bf7ccef03239554c00244b"]
    },
    {
      "_id": "63bf7ac9f03239cf1b00169b",
      "price": "$87.49",
      "expense": "$8.74",
      "transactions": ["63bf7ccef03239343e0016ac", "63bf7ccef0323937a5001698"]
    },
    {
      "_id": "63bf7ac9f03239cf1b00169c",
      "price": "$34.52",
      "expense": "$2.31",
      "transactions": ["63bf7ccef03239aec9001562", "63bf7ccef0323937a500168d"]
    },
    {
      "_id": "63bf7ac9f03239cf1b00169d",
      "price": "$90.83",
      "expense": "$7.83",
      "transactions": [
        "63bf7ccef0323975d6001698",
        "63bf7ccef032394f5f002439",
        "63bf7ccef03239e00200160f",
        "63bf7ccef0323975d600169b",
        "63bf7ccef03239aec9001557"
      ]
    },
    {
      "_id": "63bf7ac9f03239aec9001551",
      "price": "$181.98",
      "expense": "$3.02",
      "transactions": [
        "63bf7ccef032395ccf001698",
        "63bf7ccef03239343e0016ab",
        "63bf7ccef0323975d60016a2",
        "63bf7ccef03239cf1b0016a7"
      ]
    },
    {
      "_id": "63bf7ac9f03239aec9001552",
      "price": "$62.17",
      "expense": "$9.52",
      "transactions": ["63bf7ccef03239855d00155e", "63bf7ccef03239966c00169e"]
    },
    {
      "_id": "63bf7ac9f03239aec9001553",
      "price": "$83.76",
      "expense": "$1.09",
      "transactions": [
        "63bf7ccef0323975d60016a3",
        "63bf7ccef032394f5f002444",
        "63bf7ccef03239554c002450",
        "63bf7ccef032395ccf00169b"
      ]
    },
    {
      "_id": "63bf7ac9f03239aec9001554",
      "price": "$62.47",
      "expense": "$2.38",
      "transactions": [
        "63bf7ccef03239eb9d0016e4",
        "63bf7ccef03239eb9d0016d0",
        "63bf7ccef03239966c00169b",
        "63bf7ccef03239eb9d0016d5",
        "63bf7ccef0323975d6001698"
      ]
    },
    {
      "_id": "63bf7ac9f03239aec9001555",
      "price": "$54.68",
      "expense": "$5.12",
      "transactions": [
        "63bf7ccef032396d89000013",
        "63bf7ccef0323974200016a7",
        "63bf7ccef0323922d2001699",
        "63bf7ccef03239e002001608"
      ]
    },
    {
      "_id": "63bf7ac9f03239aec9001556",
      "price": "$91.72",
      "expense": "$4.73",
      "transactions": [
        "63bf7ccef03239cf1b0016a3",
        "63bf7ccef032394f5f00243e",
        "63bf7ccef0323974200016a2"
      ]
    },
    {
      "_id": "63bf7ac9f03239554c002443",
      "price": "$159.65",
      "expense": "$3.79",
      "transactions": [
        "63bf7ccef03239554c00244e",
        "63bf7ccef03239855d001561",
        "63bf7ccef032395ccf00169b",
        "63bf7ccef03239343e0016aa",
        "63bf7ccef032394f5f002439"
      ]
    },
    {
      "_id": "63bf7ac9f03239554c002444",
      "price": "$190.89",
      "expense": "$5.24",
      "transactions": [
        "63bf7ccef03239343e0016a2",
        "63bf7ccef0323974200016a3",
        "63bf7ccef0323922d200169c",
        "63bf7ccef03239966c00169e",
        "63bf7ccef03239cf1b0016a7"
      ]
    },
    {
      "_id": "63bf7ac9f03239554c002445",
      "price": "$155.13",
      "expense": "$1.68",
      "transactions": [
        "63bf7ccef03239cf1b00169f",
        "63bf7ccef03239966c00169f",
        "63bf7ccef0323937a5001697",
        "63bf7ccef0323975d60016a2"
      ]
    },
    {
      "_id": "63bf7ac9f03239554c002446",
      "price": "$43.82",
      "expense": "$7.85",
      "transactions": [
        "63bf7ccef03239eb9d0016dd",
        "63bf7ccef0323901e6001557"
      ]
    },
    {
      "_id": "63bf7ac9f03239554c002447",
      "price": "$58.31",
      "expense": "$9.94",
      "transactions": [
        "63bf7ccef03239cf1b0016a6",
        "63bf7ccef03239966c00169a",
        "63bf7ccef0323974200016a1",
        "63bf7ccef0323975d600169c"
      ]
    },
    {
      "_id": "63bf7ac9f03239554c002448",
      "price": "$138.47",
      "expense": "$6.40",
      "transactions": [
        "63bf7ccef032397b4f001606",
        "63bf7ccef03239f920001691",
        "63bf7ccef03239966c001698"
      ]
    },
    {
      "_id": "63bf7ac9f032397420001696",
      "price": "$10.40",
      "expense": "$3.20",
      "transactions": [
        "63bf7ccef03239966c00169a",
        "63bf7ccef032396d89000013",
        "63bf7ccef03239eb9d0016d6",
        "63bf7ccef032396a8e00169e"
      ]
    },
    {
      "_id": "63bf7ac9f032397420001697",
      "price": "$22.48",
      "expense": "$5.36",
      "transactions": [
        "63bf7ccef03239cf1b0016a6",
        "63bf7ccef03239eb9d0016df"
      ]
    },
    {
      "_id": "63bf7ac9f032397420001698",
      "price": "$92.16",
      "expense": "$9.12",
      "transactions": [
        "63bf7ccef03239cf1b0016a9",
        "63bf7ccef032396d89000015",
        "63bf7ccef03239f920001691",
        "63bf7ccef03239f920001699"
      ]
    },
    {
      "_id": "63bf7ac9f032397420001699",
      "price": "$140.77",
      "expense": "$9.02",
      "transactions": [
        "63bf7ccef0323974200016a2",
        "63bf7ccef032395ccf00169c",
        "63bf7ccef0323937a500168d"
      ]
    },
    {
      "_id": "63bf7ac9f03239742000169a",
      "price": "$100.62",
      "expense": "$6.55",
      "transactions": [
        "63bf7ccef032394f5f002442",
        "63bf7ccef0323922d2001695",
        "63bf7ccef032395ccf001696",
        "63bf7ccef0323974200016a7"
      ]
    },
    {
      "_id": "63bf7ac9f03239742000169b",
      "price": "$69.13",
      "expense": "$6.26",
      "transactions": [
        "63bf7ccef03239eb9d0016d0",
        "63bf7ccef0323975d600169c",
        "63bf7ccef03239cf1b0016a8"
      ]
    },
    {
      "_id": "63bf7ac9f03239966c001692",
      "price": "$124.82",
      "expense": "$8.49",
      "transactions": [
        "63bf7ccef03239eb9d0016de",
        "63bf7ccef03239eb9d0016d3",
        "63bf7ccef0323974200016a7",
        "63bf7ccef032396d8900000e",
        "63bf7ccef032397b4f001607"
      ]
    },
    {
      "_id": "63bf7ac9f03239966c001693",
      "price": "$196.68",
      "expense": "$3.32",
      "transactions": [
        "63bf7ccef03239554c002452",
        "63bf7ccef0323922d2001698",
        "63bf7ccef03239aec9001562",
        "63bf7ccef03239855d00155f",
        "63bf7ccef0323901e600155f"
      ]
    },
    {
      "_id": "63bf7ac9f03239966c001694",
      "price": "$172.48",
      "expense": "$2.38",
      "transactions": [
        "63bf7ccef032394cbd0016a0",
        "63bf7ccef03239343e0016aa",
        "63bf7ccef032395ccf00169a",
        "63bf7ccef03239554c00244d",
        "63bf7ccef032396a8e001699"
      ]
    },
    {
      "_id": "63bf7ac9f03239966c001695",
      "price": "$112.84",
      "expense": "$4.34",
      "transactions": [
        "63bf7ccef032396d89000013",
        "63bf7ccef03239554c00244c"
      ]
    },
    {
      "_id": "63bf7ac9f03239966c001696",
      "price": "$37.97",
      "expense": "$5.76",
      "transactions": [
        "63bf7ccef032394f5f002440",
        "63bf7ccef03239eb9d0016df",
        "63bf7ccef0323937a5001694",
        "63bf7ccef032396a8e001698",
        "63bf7ccef032396a8e001696"
      ]
    },
    {
      "_id": "63bf7ac9f03239966c001697",
      "price": "$123.72",
      "expense": "$2.85",
      "transactions": [
        "63bf7ccef03239eb9d0016e3",
        "63bf7ccef0323974200016a6",
        "63bf7ccef0323937a5001691"
      ]
    },
    {
      "_id": "63bf7ac9f0323975d6001692",
      "price": "$15.02",
      "expense": "$2.00",
      "transactions": [
        "63bf7ccef032396a8e001697",
        "63bf7ccef0323975d6001698"
      ]
    },
    {
      "_id": "63bf7ac9f0323975d6001693",
      "price": "$19.69",
      "expense": "$2.65",
      "transactions": [
        "63bf7ccef0323937a500168e"
      ]
    },
    [
      {
        "_id": "63bf7ac9f0323975d6001694",
        "price": "$30.80",
        "expense": "$5.02",
        "transactions": [
          "63bf7ccef0323975d600169f",
          "63bf7ccef032394f5f002440",
          "63bf7ccef032396a8e001695",
          "63bf7ccef03239742000169c"
        ]
      },
      {
        "_id": "63bf7ac9f0323975d6001695",
        "price": "$90.56",
        "expense": "$2.93",
        "transactions": [
          "63bf7ccef0323975d600169d"
        ]
      },
      {
        "_id": "63bf7ac9f0323975d6001696",
        "price": "$30.37",
        "expense": "$8.63",
        "transactions": [
          "63bf7ccef0323922d200169c",
          "63bf7ccef0323974200016a5",
          "63bf7ccef032394f5f002443"
        ]
      },
      {
        "_id": "63bf7ac9f0323975d6001697",
        "price": "$149.26",
        "expense": "$1.33",
        "transactions": [
          "63bf7ccef03239554c00244d",
          "63bf7ccef03239e002001606",
          "63bf7ccef03239eb9d0016d6",
          "63bf7ccef03239966c00169e"
        ]
      },
      {
        "_id": "63bf7ac9f032396a8e00168e",
        "price": "$167.45",
        "expense": "$9.30",
        "transactions": [
          "63bf7ccef0323937a5001693",
          "63bf7ccef03239343e0016a9",
          "63bf7ccef032397b4f001608"
        ]
      },
      {
        "_id": "63bf7ac9f032396a8e00168f",
        "price": "$50.36",
        "expense": "$4.38",
        "transactions": [
          "63bf7ccef032394f5f00243f"
        ]
      },
      {
        "_id": "63bf7ac9f032396a8e001690",
        "price": "$151.61",
        "expense": "$2.27",
        "transactions": [
          "63bf7ccef03239966c001699",
          "63bf7ccef03239742000169f"
        ]
      },
      {
        "_id": "63bf7ac9f032396a8e001691",
        "price": "$191.46",
        "expense": "$5.60",
        "transactions": [
          "63bf7ccef0323901e600155f"
        ]
      },
      {
        "_id": "63bf7ac9f032396a8e001692",
        "price": "$131.96",
        "expense": "$8.80",
        "transactions": [
          "63bf7ccef032397b4f001605",
          "63bf7ccef03239855d001561",
          "63bf7ccef03239eb9d0016d9",
          "63bf7ccef0323901e6001558",
          "63bf7ccef032394f5f002444"
        ]
      },
      {
        "_id": "63bf7ac9f032396a8e001693",
        "price": "$164.96",
        "expense": "$4.16",
        "transactions": [
          "63bf7ccef03239eb9d0016d8"
        ]
      },
      {
        "_id": "63bf7ac9f032395ccf00168e",
        "price": "$13.57",
        "expense": "$5.18",
        "transactions": [
          "63bf7ccef032395ccf001695"
        ]
      },
      {
        "_id": "63bf7ac9f032395ccf00168f",
        "price": "$177.57",
        "expense": "$7.04",
        "transactions": [
          "63bf7ccef0323922d2001698",
          "63bf7ccef03239855d00155c"
        ]
      },
      {
        "_id": "63bf7ac9f032395ccf001690",
        "price": "$172.71",
        "expense": "$5.73",
        "transactions": [
          "63bf7ccef03239966c00169d"
        ]
      },
      {
        "_id": "63bf7ac9f032395ccf001691",
        "price": "$17.48",
        "expense": "$4.81",
        "transactions": [
          "63bf7ccef0323974200016a0",
          "63bf7ccef0323937a5001692"
        ]
      },
      {
        "_id": "63bf7ac9f032395ccf001692",
        "price": "$54.13",
        "expense": "$7.44",
        "transactions": [
          "63bf7ccef0323922d2001694",
          "63bf7ccef03239eb9d0016df"
        ]
      },
      {
        "_id": "63bf7ac9f032395ccf001693",
        "price": "$155.93",
        "expense": "$9.10",
        "transactions": [
          "63bf7ccef03239343e0016a7",
          "63bf7ccef032394f5f002440",
          "63bf7ccef03239cf1b0016a9",
          "63bf7ccef032395ccf00169a"
        ]
      },
      {
        "_id": "63bf7ac9f032397b4f0015fb",
        "price": "$13.34",
        "expense": "$6.17",
        "transactions": [
          "63bf7ccef03239cf1b0016a4"
        ]
      },
      {
        "_id": "63bf7ac9f032397b4f0015fc",
        "price": "$75.89",
        "expense": "$1.11",
        "transactions": [
          "63bf7ccef03239aec900155f",
          "63bf7ccef03239966c0016a0",
          "63bf7ccef03239cf1b00169f",
          "63bf7ccef032394f5f002440"
        ]
      },
      {
        "_id": "63bf7ac9f032397b4f0015fd",
        "price": "$153.85",
        "expense": "$6.99",
        "transactions": [
          "63bf7ccef03239343e0016a3",
          "63bf7ccef0323974200016a3",
          "63bf7ccef0323975d600169c",
          "63bf7ccef03239742000169c",
          "63bf7ccef03239cf1b0016a3"
        ]
      },
      {
        "_id": "63bf7ac9f032397b4f0015fe",
        "price": "$187.83",
        "expense": "$6.66",
        "transactions": [
          "63bf7ccef0323937a5001692",
          "63bf7ccef03239aec9001559",
          "63bf7ccef0323922d200169b",
          "63bf7ccef0323922d200169c"
        ]
      },
      {
        "_id": "63bf7ac9f032397b4f0015ff",
        "price": "$119.33",
        "expense": "$1.40",
        "transactions": [
          "63bf7ccef032397b4f00160b",
          "63bf7ccef03239eb9d0016ce",
          "63bf7ccef03239eb9d0016d3",
          "63bf7ccef032397b4f001602",
          "63bf7ccef03239cf1b0016a7"
        ]
      },
      {
        "_id": "63bf7ac9f032397b4f001600",
        "price": "$54.00",
        "expense": "$5.61",
        "transactions": [
          "63bf7ccef03239554c002454",
          "63bf7ccef032394cbd0016a9"
        ]
      },
      {
        "_id": "63bf7ac9f0323922d200168e",
        "price": "$144.81",
        "expense": "$7.45",
        "transactions": [
          "63bf7ccef032395ccf00169b",
          "63bf7ccef03239eb9d0016dd",
          "63bf7ccef03239eb9d0016d4"
        ]
      },
      {
        "_id": "63bf7ac9f0323922d200168f",
        "price": "$37.04",
        "expense": "$5.86",
        "transactions": [
          "63bf7ccef0323974200016a5"
        ]
      },
      {
        "_id": "63bf7ac9f0323922d2001690",
        "price": "$161.03",
        "expense": "$4.48",
        "transactions": [
          "63bf7ccef03239966c00169a"
        ]
      },
      {
        "_id": "63bf7ac9f0323922d2001691",
        "price": "$73.46",
        "expense": "$7.95",
        "transactions": [
          "63bf7ccef032395ccf001696",
          "63bf7ccef03239eb9d0016de",
          "63bf7ccef03239f92000168f",
          "63bf7ccef032394f5f00243e",
          "63bf7ccef032394cbd0016a5"
        ]
      },
      {
        "_id": "63bf7ac9f0323922d2001692",
        "price": "$120.96",
        "expense": "$8.90",
        "transactions": [
          "63bf7ccef032396a8e00169e",
          "63bf7ccef032397b4f001603"
        ]
      },
      {
        "_id": "63bf7ac9f0323922d2001693",
        "price": "$34.46",
        "expense": "$9.25",
        "transactions": [
          "63bf7ccef032396d89000012",
          "63bf7ccef03239f920001697",
          "63bf7ccef0323937a5001694",
          "63bf7ccef03239855d00155b",
          "63bf7ccef032395ccf001697"
        ]
      },
      {
        "_id": "63bf7ac9f032396d89000007",
        "price": "$172.27",
        "expense": "$3.92",
        "transactions": [
          "63bf7ccef03239554c00244b"
        ]
      },
      {
        "_id": "63bf7ac9f032396d89000008",
        "price": "$20.54",
        "expense": "$8.12",
        "transactions": [
          "63bf7ccef03239855d001558"
        ]
      },
      {
        "_id": "63bf7ac9f032396d89000009",
        "price": "$80.31",
        "expense": "$7.04",
        "transactions": [
          "63bf7ccef0323901e6001558",
          "63bf7ccef0323937a5001693",
          "63bf7ccef03239eb9d0016d9"
        ]
      },
      {
        "_id": "63bf7ac9f032396d8900000a",
        "price": "$77.67",
        "expense": "$4.14",
        "transactions": ["63bf7ccef03239343e0016ab"]
      },
      {
        "_id": "63bf7ac9f032396d8900000b",
        "price": "$47.25",
        "expense": "$5.53",
        "transactions": ["63bf7ccef03239343e0016a8", "63bf7ccef032394f5f00243e"]
      },
      {
        "_id": "63bf7ac9f032396d8900000c",
        "price": "$181.02",
        "expense": "$7.57",
        "transactions": [
          "63bf7ccef0323922d2001698",
          "63bf7ccef03239eb9d0016e3",
          "63bf7ccef032396a8e00169c",
          "63bf7ccef032397b4f001608",
          "63bf7ccef032396d89000013"
        ]
      },
      {
        "_id": "63bf7ac9f03239f920001689",
        "price": "$67.20",
        "expense": "$8.37",
        "transactions": [
          "63bf7ccef032396a8e00169b",
          "63bf7ccef03239343e0016a2",
          "63bf7ccef03239966c00169d",
          "63bf7ccef0323922d2001698",
          "63bf7ccef03239855d001561"
        ]
      },
      {
        "_id": "63bf7ac9f03239f92000168a",
        "price": "$58.15",
        "expense": "$3.19",
        "transactions": ["63bf7ccef03239f920001690"]
      },
      {
        "_id": "63bf7ac9f03239f92000168b",
        "price": "$145.65",
        "expense": "$3.83",
        "transactions": ["63bf7ccef032394cbd0016aa"]
      },
      {
        "_id": "63bf7ac9f03239f92000168c",
        "price": "$134.08",
        "expense": "$7.03",
        "transactions": [
          "63bf7ccef032396a8e00169a",
          "63bf7ccef032397b4f001604",
          "63bf7ccef03239eb9d0016d1",
          "63bf7ccef03239cf1b0016a7",
          "63bf7ccef03239eb9d0016ea"
        ]
      },
      {
        "_id": "63bf7ac9f03239f92000168d",
        "price": "$33.79",
        "expense": "$4.54",
        "transactions": [
          "63bf7ccef032394cbd0016a1",
          "63bf7ccef0323922d200169d",
          "63bf7ccef03239cf1b0016a1",
          "63bf7ccef0323975d60016a3",
          "63bf7ccef03239aec9001557"
        ]
      },
      {
        "_id": "63bf7ac9f03239f92000168e",
        "price": "$182.10",
        "expense": "$9.54",
        "transactions": [
          "63bf7ccef032396a8e001698",
          "63bf7ccef0323922d2001699",
          "63bf7ccef03239742000169c",
          "63bf7ccef03239aec900155d"
        ]
      },
      {
        "_id": "63bf7ac9f032394f5f002433",
        "price": "$129.93",
        "expense": "$1.15",
        "transactions": [
          "63bf7ccef0323975d600169a",
          "63bf7ccef032397b4f001604",
          "63bf7ccef03239966c001699",
          "63bf7ccef032397b4f001603"
        ]
      },
      {
        "_id": "63bf7ac9f032394f5f002434",
        "price": "$148.47",
        "expense": "$1.63",
        "transactions": [
          "63bf7ccef03239554c00244e",
          "63bf7ccef032395ccf00169f",
          "63bf7ccef0323937a500168d",
          "63bf7ccef0323975d60016a1"
        ]
      },
      {
        "_id": "63bf7ac9f032394f5f002435",
        "price": "$13.52",
        "expense": "$9.76",
        "transactions": [
          "63bf7ccef03239343e0016a3",
          "63bf7ccef03239966c00169f",
          "63bf7ccef03239cf1b0016a8",
          "63bf7ccef032395ccf00169d"
        ]
      },
      {
        "_id": "63bf7ac9f032394f5f002436",
        "price": "$120.88",
        "expense": "$5.94",
        "transactions": [
          "63bf7ccef03239e00200160d",
          "63bf7ccef03239cf1b0016a1",
          "63bf7ccef032396d8900000f"
        ]
      },
      {
        "_id": "63bf7ac9f032394f5f002437",
        "price": "$153.54",
        "expense": "$9.63",
        "transactions": ["63bf7ccef03239eb9d0016d0", "63bf7ccef032396d89000010"]
      },
      {
        "_id": "63bf7ac9f032394f5f002438",
        "price": "$35.74",
        "expense": "$8.71",
        "transactions": [
          "63bf7ccef0323975d6001698",
          "63bf7ccef03239554c00244c",
          "63bf7ccef03239cf1b0016a0",
          "63bf7ccef032394f5f002442",
          "63bf7ccef03239f92000168f"
        ]
      },
      {
        "_id": "63bf7ac9f0323937a5001687",
        "price": "$120.21",
        "expense": "$5.00",
        "transactions": [
          "63bf7ccef03239554c00244a",
          "63bf7ccef032394cbd0016a1",
          "63bf7ccef03239966c00169e",
          "63bf7ccef03239742000169f",
          "63bf7ccef03239eb9d0016e2"
        ]
      },
      {
        "_id": "63bf7ac9f0323937a5001688",
        "price": "$180.06",
        "expense": "$6.39",
        "transactions": ["63bf7ccef03239554c002453"]
      },
      {
        "_id": "63bf7ac9f0323937a5001689",
        "price": "$92.70",
        "expense": "$5.53",
        "transactions": [
          "63bf7ccef03239343e0016a9",
          "63bf7ccef03239cf1b0016a1",
          "63bf7ccef032397b4f001609"
        ]
      },
      {
        "_id": "63bf7ac9f0323937a500168a",
        "price": "$35.39",
        "expense": "$2.89",
        "transactions": [
          "63bf7ccef0323937a5001694",
          "63bf7ccef03239eb9d0016da",
          "63bf7ccef0323937a5001698",
          "63bf7ccef03239eb9d0016e6"
        ]
      },
      {
        "_id": "63bf7ac9f0323937a500168b",
        "price": "$159.59",
        "expense": "$3.54",
        "transactions": [
          "63bf7ccef03239eb9d0016d9",
          "63bf7ccef032396a8e001697",
          "63bf7ccef032394cbd0016aa",
          "63bf7ccef03239f920001693"
        ]
      },
      {
        "_id": "63bf7ac9f0323937a500168c",
        "price": "$116.66",
        "expense": "$5.60",
        "transactions": [
          "63bf7ccef03239aec900155a",
          "63bf7ccef032394cbd0016a2",
          "63bf7ccef032396a8e001694",
          "63bf7ccef0323975d60016a0"
        ]
      },
      {
        "_id": "63bf7ac9f03239855d001551",
        "price": "$19.66",
        "expense": "$6.43",
        "transactions": [
          "63bf7ccef03239eb9d0016d0",
          "63bf7ccef03239554c00244e",
          "63bf7ccef0323922d2001697"
        ]
      },
      {
        "_id": "63bf7ac9f03239855d001552",
        "price": "$99.78",
        "expense": "$7.03",
        "transactions": [
          "63bf7ccef03239eb9d0016cd",
          "63bf7ccef032395ccf001697",
          "63bf7ccef03239855d001558",
          "63bf7ccef03239966c00169c",
          "63bf7ccef0323922d2001696"
        ]
      },
      {
        "_id": "63bf7ac9f03239855d001553",
        "price": "$145.56",
        "expense": "$9.40",
        "transactions": ["63bf7ccef0323922d2001694"]
      },
      {
        "_id": "63bf7ac9f03239855d001554",
        "price": "$133.65",
        "expense": "$1.03",
        "transactions": [
          "63bf7ccef0323937a5001690",
          "63bf7ccef03239f920001696",
          "63bf7ccef0323901e600155e",
          "63bf7ccef032396d89000018",
          "63bf7ccef0323901e6001560"
        ]
      },
      {
        "_id": "63bf7ac9f03239855d001555",
        "price": "$174.42",
        "expense": "$5.30",
        "transactions": ["63bf7ccef03239aec9001558"]
      },
      {
        "_id": "63bf7ac9f03239855d001556",
        "price": "$77.55",
        "expense": "$1.01",
        "transactions": ["63bf7ccef03239e002001607"]
      },
      {
        "_id": "63bf7ac9f03239eb9d0016c3",
        "price": "$103.01",
        "expense": "$6.81",
        "transactions": [
          "63bf7ccef03239966c001699",
          "63bf7ccef03239554c00244e",
          "63bf7ccef03239eb9d0016cd",
          "63bf7ccef03239cf1b0016a8",
          "63bf7ccef032394f5f00243b"
        ]
      },
      {
        "_id": "63bf7ac9f03239eb9d0016c4",
        "price": "$88.02",
        "expense": "$8.00",
        "transactions": ["63bf7ccef0323901e600155f", "63bf7ccef03239eb9d0016e6"]
      },
      {
        "_id": "63bf7ac9f03239eb9d0016c5",
        "price": "$119.84",
        "expense": "$8.95",
        "transactions": ["63bf7ccef032395ccf001695", "63bf7ccef03239f920001695"]
      },
      {
        "_id": "63bf7ac9f03239eb9d0016c6",
        "price": "$18.02",
        "expense": "$5.48",
        "transactions": [
          "63bf7ccef03239e00200160b",
          "63bf7ccef032395ccf00169a",
          "63bf7ccef03239aec9001560",
          "63bf7ccef0323901e600155e",
          "63bf7ccef03239343e0016a9"
        ]
      },
      {
        "_id": "63bf7ac9f03239eb9d0016c7",
        "price": "$121.59",
        "expense": "$7.27",
        "transactions": [
          "63bf7ccef0323975d600169b",
          "63bf7ccef032396a8e00169d",
          "63bf7ccef03239eb9d0016d5",
          "63bf7ccef03239e00200160e"
        ]
      },
      {
        "_id": "63bf7ac9f03239eb9d0016c8",
        "price": "$42.71",
        "expense": "$7.26",
        "transactions": ["63bf7ccef032396a8e001696", "63bf7ccef032397b4f001608"]
      },
      {
        "_id": "63bf7ac9f03239eb9d0016c9",
        "price": "$106.89",
        "expense": "$2.49",
        "transactions": ["63bf7ccef03239966c00169d"]
      },
      {
        "_id": "63bf7ac9f03239eb9d0016ca",
        "price": "$162.96",
        "expense": "$2.18",
        "transactions": [
          "63bf7ccef03239f920001691",
          "63bf7ccef0323937a5001693",
          "63bf7ccef03239f920001694",
          "63bf7ccef0323901e600155b"
        ]
      },
      {
        "_id": "63bf7ac9f03239eb9d0016cb",
        "price": "$102.90",
        "expense": "$1.40",
        "transactions": [
          "63bf7ccef03239966c00169f",
          "63bf7ccef032394cbd0016a6",
          "63bf7ccef032395ccf00169d",
          "63bf7ccef032395ccf00169e",
          "63bf7ccef032396a8e001697"
        ]
      },
      {
        "_id": "63bf7ac9f03239eb9d0016cc",
        "price": "$21.98",
        "expense": "$7.86",
        "transactions": [
          "63bf7ccef03239343e0016a3",
          "63bf7ccef032397b4f001606",
          "63bf7ccef0323901e6001559"
        ]
      }
    ]
    



],

  "transcatons":
  [ 
      {
    "_id": "63bf7ccef03239e002001606",
    "amount": "$154.37",
    "buyer": "Jorrie Tidswell",
    "productIds": ["63bf7ac9f03239e002001604"]
  },
  {
    "_id": "63bf7ccef03239e002001607",
    "amount": "$207.45",
    "buyer": "Alfonse Surridge",
    "productIds": [
      "63bf7ac9f032396a8e00168e",
      "63bf7ac9f032396a8e001693",
      "63bf7ac9f03239855d001555",
      "63bf7ac9f0323922d2001692"
    ]
  },
  {
    "_id": "63bf7ccef03239e002001608",
    "amount": "$23.74",
    "buyer": "Flem Domenc",
    "productIds": [
      "63bf7ac9f0323937a5001689",
      "63bf7ac9f032396a8e001692",
      "63bf7ac9f03239343e00169d",
      "63bf7ac9f03239855d001553",
      "63bf7ac9f03239cf1b001698"
    ]
  },
  {
    "_id": "63bf7ccef03239e002001609",
    "amount": "$156.67",
    "buyer": "Jordain Gilberthorpe",
    "productIds": [
      "63bf7ac9f0323975d6001692",
      "63bf7ac9f0323937a500168a",
      "63bf7ac9f0323922d2001691",
      "63bf7ac9f03239f92000168b"
    ]
  },
  {
    "_id": "63bf7ccef03239e00200160a",
    "amount": "$174.95",
    "buyer": "Thelma Christoforou",
    "productIds": [
      "63bf7ac9f032397b4f0015fd",
      "63bf7ac9f032396a8e001690",
      "63bf7ac9f03239554c002445",
      "63bf7ac9f032395ccf001692"
    ]
  },
  {
    "_id": "63bf7ccef03239e00200160b",
    "amount": "$245.32",
    "buyer": "Mattie Iuorio",
    "productIds": [
      "63bf7ac9f03239f92000168e",
      "63bf7ac9f0323975d6001693",
      "63bf7ac9f03239f920001689",
      "63bf7ac9f03239966c001696"
    ]
  },
  {
    "_id": "63bf7ccef03239e00200160c",
    "amount": "$133.57",
    "buyer": "Ancell Valerio",
    "productIds": [
      "63bf7ac9f032396a8e00168f",
      "63bf7ac9f03239343e0016a0",
      "63bf7ac9f032394cbd00169c"
    ]
  },
  {
    "_id": "63bf7ccef03239e00200160d",
    "amount": "$122.49",
    "buyer": "Ollie Bolderstone",
    "productIds": ["63bf7ac9f03239343e00169f"]
  },
  {
    "_id": "63bf7ccef03239e00200160e",
    "amount": "$270.23",
    "buyer": "Audrey Zimmermeister",
    "productIds": ["63bf7ac9f0323901e6001552"]
  },
  {
    "_id": "63bf7ccef03239e00200160f",
    "amount": "$173.38",
    "buyer": "Sibby Iacovolo",
    "productIds": [
      "63bf7ac9f032397b4f0015fe",
      "63bf7ac9f03239554c002447",
      "63bf7ac9f0323937a500168c",
      "63bf7ac9f03239e002001605",
      "63bf7ac9f032395ccf00168f"
    ]
  },
  {
    "_id": "63bf7ccef03239e002001610",
    "amount": "$283.65",
    "buyer": "Perry Scarrisbrick",
    "productIds": ["63bf7ac9f032395ccf001690", "63bf7ac9f03239343e00169e"]
  },
  {
    "_id": "63bf7ccef03239e002001611",
    "amount": "$187.80",
    "buyer": "Danika Dearth",
    "productIds": [
      "63bf7ac9f03239e002001600",
      "63bf7ac9f0323901e6001553",
      "63bf7ac9f03239aec9001554",
      "63bf7ac9f032394f5f002438"
    ]
  },
  {
    "_id": "63bf7ccef03239343e0016a1",
    "amount": "$233.90",
    "buyer": "Jeddy Juschka",
    "productIds": ["63bf7ac9f03239aec9001553", "63bf7ac9f03239aec9001554"]
  },
  {
    "_id": "63bf7ccef03239343e0016a2",
    "amount": "$217.32",
    "buyer": "Shelley Ganiford",
    "productIds": ["63bf7ac9f032396a8e001691", "63bf7ac9f0323937a500168c"]
  },
  {
    "_id": "63bf7ccef03239343e0016a3",
    "amount": "$272.71",
    "buyer": "Inigo Paddeley",
    "productIds": ["63bf7ac9f03239cf1b00169a", "63bf7ac9f03239855d001552"]
  },
  {
    "_id": "63bf7ccef03239343e0016a4",
    "amount": "$297.98",
    "buyer": "Mallorie Handrek",
    "productIds": [
      "63bf7ac9f03239f92000168b",
      "63bf7ac9f03239aec9001551",
      "63bf7ac9f03239855d001554",
      "63bf7ac9f03239554c002448"
    ]
  },
  {
    "_id": "63bf7ccef03239343e0016a5",
    "amount": "$145.37",
    "buyer": "Isadora Hollingsby",
    "productIds": [
      "63bf7ac9f03239f92000168c",
      "63bf7ac9f0323937a500168a",
      "63bf7ac9f0323901e6001554"
    ]
  },
  {
    "_id": "63bf7ccef03239343e0016a6",
    "amount": "$297.67",
    "buyer": "Claudetta McNally",
    "productIds": [
      "63bf7ac9f0323975d6001695",
      "63bf7ac9f032396a8e001690",
      "63bf7ac9f03239e002001604"
    ]
  },
  {
    "_id": "63bf7ccef03239343e0016a7",
    "amount": "$221.50",
    "buyer": "Garek Van Halen",
    "productIds": ["63bf7ac9f03239554c002447"]
  },
  {
    "_id": "63bf7ccef03239343e0016a8",
    "amount": "$296.28",
    "buyer": "Rozanna Lochead",
    "productIds": [
      "63bf7ac9f03239e002001605",
      "63bf7ac9f032396a8e00168e",
      "63bf7ac9f032394cbd001699"
    ]
  },
  {
    "_id": "63bf7ccef03239343e0016a9",
    "amount": "$270.66",
    "buyer": "Valerie Dooly",
    "productIds": [
      "63bf7ac9f032394cbd00169d",
      "63bf7ac9f032395ccf001691",
      "63bf7ac9f03239e002001601",
      "63bf7ac9f032396d89000008",
      "63bf7ac9f0323975d6001693"
    ]
  },
  {
    "_id": "63bf7ccef03239343e0016aa",
    "amount": "$70.39",
    "buyer": "Ronny Dishman",
    "productIds": ["63bf7ac9f03239cf1b00169b", "63bf7ac9f0323975d6001692"]
  },
  {
    "_id": "63bf7ccef03239343e0016ab",
    "amount": "$193.31",
    "buyer": "Carita Tampion",
    "productIds": [
      "63bf7ac9f03239eb9d0016c5",
      "63bf7ac9f032394cbd00169e",
      "63bf7ac9f032395ccf001693"
    ]
  },
  {
    "_id": "63bf7ccef03239343e0016ac",
    "amount": "$123.95",
    "buyer": "Guido Valentine",
    "productIds": ["63bf7ac9f03239cf1b00169c"]
  },
  {
    "_id": "63bf7ccef0323901e6001557",
    "amount": "$49.37",
    "buyer": "Kimberley Glassopp",
    "productIds": ["63bf7ac9f032396a8e001692"]
  },
  {
    "_id": "63bf7ccef0323901e6001558",
    "amount": "$89.87",
    "buyer": "Cloris Vasyushkhin",
    "productIds": [
      "63bf7ac9f03239343e00169d",
      "63bf7ac9f0323922d2001691",
      "63bf7ac9f032396a8e001693",
      "63bf7ac9f03239343e00169f",
      "63bf7ac9f03239855d001551"
    ]
  },
  {
    "_id": "63bf7ccef0323901e6001559",
    "amount": "$72.12",
    "buyer": "Chevy Richardet",
    "productIds": ["63bf7ac9f0323937a5001687"]
  },
  {
    "_id": "63bf7ccef0323901e600155a",
    "amount": "$271.82",
    "buyer": "Ailis Bum",
    "productIds": [
      "63bf7ac9f03239554c002448",
      "63bf7ac9f032394cbd001699",
      "63bf7ac9f03239343e00169c"
    ]
  },
  {
    "_id": "63bf7ccef0323901e600155b",
    "amount": "$282.33",
    "buyer": "Florance Flook",
    "productIds": [
      "63bf7ac9f03239aec9001554",
      "63bf7ac9f03239f920001689",
      "63bf7ac9f03239f92000168c",
      "63bf7ac9f03239e002001601"
    ]
  },
  {
    "_id": "63bf7ccef0323901e600155c",
    "amount": "$177.35",
    "buyer": "Agna Tresvina",
    "productIds": [
      "63bf7ac9f03239742000169b",
      "63bf7ac9f03239966c001695",
      "63bf7ac9f03239966c001694",
      "63bf7ac9f032397420001698"
    ]
  },
  {
    "_id": "63bf7ccef03239aec9001561",
    "amount": "$158.49",
    "buyer": "Curcio Vaines",
    "productIds": [
      "63bf7ac9f03239eb9d0016c8",
      "63bf7ac9f03239742000169a",
      "63bf7ac9f0323937a5001689",
      "63bf7ac9f03239eb9d0016cc",
      "63bf7ac9f032394f5f002433"
    ]
  },
  {
    "_id": "63bf7ccef03239aec9001562",
    "amount": "$64.71",
    "buyer": "Del Coveny",
    "productIds": [
      "63bf7ac9f032397b4f0015ff",
      "63bf7ac9f03239cf1b001699",
      "63bf7ac9f03239554c002447",
      "63bf7ac9f03239e002001602"
    ]
  },
  {
    "_id": "63bf7ccef032394cbd00169f",
    "amount": "$195.92",
    "buyer": "Juliette Whiteside",
    "productIds": [
      "63bf7ac9f03239855d001552",
      "63bf7ac9f032394cbd00169d"
    ]
  },
  {
    "_id": "63bf7ccef032394cbd0016a0",
    "amount": "$10.22",
    "buyer": "Licha Mewis",
    "productIds": [
      "63bf7ac9f032394f5f002438",
      "63bf7ac9f03239eb9d0016c3",
      "63bf7ac9f03239e002001604"
    ]
  },
  {
    "_id": "63bf7ccef032394cbd0016a1",
    "amount": "$176.47",
    "buyer": "Freedman Basnett",
    "productIds": [
      "63bf7ac9f03239f92000168a",
      "63bf7ac9f0323937a500168a",
      "63bf7ac9f03239742000169a",
      "63bf7ac9f032394cbd00169a"
    ]
  },
  {
    "_id": "63bf7ccef032394cbd0016a2",
    "amount": "$283.94",
    "buyer": "Dex Martinat",
    "productIds": [
      "63bf7ac9f03239343e0016a0",
      "63bf7ac9f0323922d200168e",
      "63bf7ac9f03239343e00169d"
    ]
  },
  {
    "_id": "63bf7ccef032394cbd0016a3",
    "amount": "$135.62",
    "buyer": "Mal Hessing",
    "productIds": [
      "63bf7ac9f03239f92000168e",
      "63bf7ac9f03239aec9001552",
      "63bf7ac9f03239855d001554",
      "63bf7ac9f03239e002001603",
      "63bf7ac9f0323901e6001556"
    ]
  },
  {
    "_id": "63bf7ccef032394cbd0016a4",
    "amount": "$87.83",
    "buyer": "Kenyon Lake",
    "productIds": [
      "63bf7ac9f0323975d6001697",
      "63bf7ac9f03239966c001696",
      "63bf7ac9f03239966c001693"
    ]
  },
  {
    "_id": "63bf7ccef032394cbd0016a5",
    "amount": "$114.41",
    "buyer": "Winifield Ahmed",
    "productIds": [
      "63bf7ac9f032397b4f0015fb",
      "63bf7ac9f03239855d001555",
      "63bf7ac9f03239f92000168c",
      "63bf7ac9f03239966c001692",
      "63bf7ac9f03239e002001601"
    ]
  },
  {
    "_id": "63bf7ccef032394cbd0016a6",
    "amount": "$263.24",
    "buyer": "Stace Igglesden",
    "productIds": [
      "63bf7ac9f032396d8900000b",
      "63bf7ac9f03239f92000168b",
      "63bf7ac9f032396d89000008",
      "63bf7ac9f03239eb9d0016c4"
    ]
  },
  {
    "_id": "63bf7ccef032394cbd0016a7",
    "amount": "$117.52",
    "buyer": "Jordan Skillern",
    "productIds": [
      "63bf7ac9f0323901e6001555"
    ]
  },
  {
    "_id": "63bf7ccef032394cbd0016a8",
    "amount": "$64.63",
    "buyer": "Yorker Sharphurst",
    "productIds": [
      "63bf7ac9f03239343e00169c",
      "63bf7ac9f0323975d6001694",
      "63bf7ac9f03239554c002444",
      "63bf7ac9f032396a8e001690",
      "63bf7ac9f03239cf1b00169d"
    ]
  },
  {
    "_id": "63bf7ccef032394cbd0016a9",
    "amount": "$180.19",
    "buyer": "Stormy Timoney",
    "productIds": [
      "63bf7ac9f032394cbd00169c",
      "63bf7ac9f032396a8e001693",
      "63bf7ac9f032395ccf001690",
      "63bf7ac9f0323901e6001552"
    ]
  },
  {
    "_id": "63bf7ccef032394cbd0016aa",
    "amount": "$70.70",
    "buyer": "Reginauld Brinicombe",
    "productIds": [
      "63bf7ac9f03239eb9d0016c5",
      "63bf7ac9f03239855d001553",
      "63bf7ac9f03239343e00169b"
    ]
  },
  {
    "_id": "63bf7ccef03239cf1b00169e",
    "amount": "$49.60",
    "buyer": "Benedikt Gibbe",
    "productIds": [
      "63bf7ac9f03239eb9d0016c5",
      "63bf7ac9f03239aec9001554",
      "63bf7ac9f0323901e6001556"
    ]
  },
  {
    "_id": "63bf7ccef03239cf1b00169f",
    "amount": "$64.19",
    "buyer": "Elia Kenningham",
    "productIds": [
      "63bf7ac9f032397b4f0015fb",
      "63bf7ac9f03239aec9001556",
      "63bf7ac9f03239855d001554"
    ]
  },
  {
    "_id": "63bf7ccef03239cf1b0016a0",
    "amount": "$275.70",
    "buyer": "Kenyon Harbour",
    "productIds": [
      "63bf7ac9f03239855d001553",
      "63bf7ac9f03239e002001603",
      "63bf7ac9f03239966c001694"
    ]
  },
  {
    "_id": "63bf7ccef03239cf1b0016a1",
    "amount": "$92.02",
    "buyer": "Willabella Bilbrey",
    "productIds": [
      "63bf7ac9f0323901e6001552",
      "63bf7ac9f032396a8e001693",
      "63bf7ac9f03239966c001695",
      "63bf7ac9f032396d8900000b",
      "63bf7ac9f03239e002001605"
    ]
  },
  {
    "_id": "63bf7ccef03239cf1b0016a2",
    "amount": "$164.62",
    "buyer": "Sax Caselli",
    "productIds": [
      "63bf7ac9f032396d8900000a",
      "63bf7ac9f03239cf1b00169c"
    ]
  },
  {
    "_id": "63bf7ccef03239cf1b0016a3",
    "amount": "$245.43",
    "buyer": "Burr D'Aulby",
    "productIds": [
      "63bf7ac9f03239aec9001552",
      "63bf7ac9f0323975d6001695"
    ]
  },
  {
    "_id": "63bf7ccef03239cf1b0016a4",
    "amount": "$266.98",
    "buyer": "Maribeth Quiddinton",
    "productIds": [
      "63bf7ac9f03239966c001692",
      "63bf7ac9f0323937a5001689",
      "63bf7ac9f032394cbd00169c",
      "63bf7ac9f0323922d2001691",
      "63bf7ac9f03239554c002443"
    ]
  },
  {
    "_id": "63bf7ccef03239cf1b0016a5",
    "amount": "$121.31",
    "buyer": "Doralia Fogg",
    "productIds": [
      "63bf7ac9f03239343e00169d",
      "63bf7ac9f032394f5f002434"
    ]
  },
  {
    "_id": "63bf7ccef03239cf1b0016a6",
    "amount": "$282.87",
    "buyer": "Gianna Malkinson",
    "productIds": [
      "63bf7ac9f03239aec9001551",
      "63bf7ac9f0323975d6001693",
      "63bf7ac9f032396a8e001691"
    ]
  },
  {
    "_id": "63bf7ccef03239cf1b0016a7",
    "amount": "$86.12",
    "buyer": "Daria Ramble",
    "productIds": [
      "63bf7ac9f0323937a500168a",
      "63bf7ac9f03239e002001604",
      "63bf7ac9f03239855d001551",
      "63bf7ac9f032395ccf001693",
      "63bf7ac9f032394cbd00169a"
    ]
  },
  {
    "_id": "63bf7ccef03239cf1b0016a8",
    "amount": "$59.70",
    "buyer": "Sile Pettinger",
    "productIds": [
      "63bf7ac9f03239e002001601",
      "63bf7ac9f03239855d001552",
      "63bf7ac9f032397420001698"
    ]
  },
  {
    "_id": "63bf7ccef03239cf1b0016a9",
    "amount": "$87.28",
    "buyer": "Barny Aldrick",
    "productIds": [
      "63bf7ac9f032397b4f001600",
      "63bf7ac9f03239eb9d0016ca",
      "63bf7ac9f03239554c002447",
      "63bf7ac9f032397b4f0015fc"
    ]
  },
  {
    "_id": "63bf7ccef03239aec9001557",
    "amount": "$10.68",
    "buyer": "Marylee Emanueli",
    "productIds": [
      "63bf7ac9f032396d8900000a",
      "63bf7ac9f03239343e00169c",
      "63bf7ac9f03239554c002448"
    ]
  },
  {
    "_id": "63bf7ccef03239aec9001558",
    "amount": "$116.97",
    "buyer": "Skell Rumbold",
    "productIds": [
      "63bf7ac9f03239aec9001553",
      "63bf7ac9f0323937a5001688",
      "63bf7ac9f03239cf1b00169d",
      "63bf7ac9f03239eb9d0016c3",
      "63bf7ac9f032394cbd00169c"
    ]
  },
  {
    "_id": "63bf7ccef03239aec9001559",
    "amount": "$97.54",
    "buyer": "Peg Flattman",
    "productIds": [
      "63bf7ac9f03239f92000168a",
      "63bf7ac9f03239cf1b00169a"
    ]
  },
  {
    "_id": "63bf7ccef03239aec900155a",
    "amount": "$237.00",
    "buyer": "Guenna Allonby",
    "productIds": [
      "63bf7ac9f032397420001698",
      "63bf7ac9f03239f920001689"
    ]
  },
  {
    "_id": "63bf7ccef03239aec900155b",
    "amount": "$19.63",
    "buyer": "Jaquenette Tunnacliffe",
    "productIds": [
      "63bf7ac9f032394cbd001699",
      "63bf7ac9f032394f5f002438"
    ]
  },
  {
    "_id": "63bf7ccef03239aec900155c",
    "amount": "$81.94",
    "buyer": "Adelind Bloan",
    "productIds": [
      "63bf7ac9f0323975d6001697",
      "63bf7ac9f032394f5f002433",
      "63bf7ac9f032396a8e001690",
      "63bf7ac9f03239cf1b00169b"
    ]
  },
  {
    "_id": "63bf7ccef03239aec900155d",
    "amount": "$245.16",
    "buyer": "Mikaela Murrish",
    "productIds": [
      "63bf7ac9f03239e002001605",
      "63bf7ac9f032397b4f0015fd",
      "63bf7ac9f0323975d6001694"
    ]
  },
  {
    "_id": "63bf7ccef03239aec900155e",
    "amount": "$153.99",
    "buyer": "Page Allom",
    "productIds": [
      "63bf7ac9f03239eb9d0016c9",
      "63bf7ac9f03239343e00169e"
    ]
  },
  {
    "_id": "63bf7ccef03239aec900155f",
    "amount": "$230.26",
    "buyer": "Rafael Haughin",
    "productIds": [
      "63bf7ac9f0323975d6001695",
      "63bf7ac9f0323901e6001552",
      "63bf7ac9f03239eb9d0016cc",
      "63bf7ac9f032396a8e001693"
    ]
  },
  {
    "_id": "63bf7ccef03239aec9001560",
    "amount": "$200.80",
    "buyer": "Branden Ossenna",
    "productIds": [
      "63bf7ac9f03239eb9d0016cb",
      "63bf7ac9f0323901e6001554",
      "63bf7ac9f032394f5f002437",
      "63bf7ac9f0323901e6001556",
      "63bf7ac9f032396a8e001691"
    ]
  },
  {
    "_id": "63bf7ccef0323974200016a6",
    "amount": "$10.21",
    "buyer": "Faythe Crickmoor",
    "productIds": [
      "63bf7ac9f032397b4f0015fe",
      "63bf7ac9f0323975d6001697",
      "63bf7ac9f032394f5f002433"
    ]
  },
  {
    "_id": "63bf7ccef0323974200016a7",
    "amount": "$16.77",
    "buyer": "Brockie Ivanyutin",
    "productIds": [
      "63bf7ac9f032394f5f002438",
      "63bf7ac9f03239554c002446"
    ]
  },
  {
    "_id": "63bf7ccef0323974200016a8",
    "amount": "$246.22",
    "buyer": "Bette-ann Clowser",
    "productIds": [
      "63bf7ac9f032394f5f002434",
      "63bf7ac9f03239cf1b00169a",
      "63bf7ac9f032394cbd001699",
      "63bf7ac9f03239aec9001557"
    ]
  },
  {
    "_id": "63bf7ccef0323974200016a9",
    "amount": "$89.98",
    "buyer": "Kerry Southcott",
    "productIds": [
      "63bf7ac9f03239cf1b00169f",
      "63bf7ac9f032396a8e001691",
      "63bf7ac9f0323937a500168b"
    ]
  },
  {
    "_id": "63bf7ccef0323974200016aa",
    "amount": "$206.57",
    "buyer": "Sydel Geddis",
    "productIds": [
      "63bf7ac9f03239f92000168d",
      "63bf7ac9f032396a8e001691",
      "63bf7ac9f032397420001696",
      "63bf7ac9f03239aec9001560",
      "63bf7ac9f03239855d001554"
    ]
  },
  {
    "_id": "63bf7ccef0323974200016ab",
    "amount": "$12.94",
    "buyer": "Jillene Plyming",
    "productIds": [
      "63bf7ac9f0323937a500168a",
      "63bf7ac9f032395ccf001690",
      "63bf7ac9f03239cf1b00169d"
    ]
  },
  {
    "_id": "63bf7ccef0323974200016ac",
    "amount": "$66.32",
  "buyer": "Karlan Lemanu",
  "productIds": [
      "63bf7ac9f03239aec9001561",
      "63bf7ac9f032394f5f002436",
      "63bf7ac9f0323901e6001553"
  ]
},
{
  "_id": "63bf7ccef0323974200016ad",
  "amount": "$131.16",
  "buyer": "Skippie Porcher",
  "productIds": [
      "63bf7ac9f032394cbd0016a9",
      "63bf7ac9f03239aec9001558",
      "63bf7ac9f03239f92000168a",
      "63bf7ac9f032397420001698"
  ]
},
{
  "_id": "63bf7ccef0323974200016ae",
  "amount": "$182.15",
  "buyer": "Merna Bode",
  "productIds": [
      "63bf7ac9f032397b4f0015fc",
      "63bf7ac9f03239742000169b",
      "63bf7ac9f03239742000169e",
      "63bf7ac9f03239aec900155b",
      "63bf7ac9f03239aec900155c"
  ]
},
{
  "_id": "63bf7ccef0323974200016af",
  "amount": "$170.29",
  "buyer": "Christabella Stoll",
  "productIds": [
      "63bf7ac9f032394f5f002433",
      "63bf7ac9f032397b4f0015fd"
  ]
},
{
  "_id": "63bf7ccef0323974200016b0",
  "amount": "$267.89",
  "buyer": "Marvin Mateiko",
  "productIds": [
      "63bf7ac9f032394cbd001699",
      "63bf7ac9f03239f920001689",
      "63bf7ac9f032394f5f002438",
      "63bf7ac9f0323901e600155d",
      "63bf7ac9f032394f5f002434"
  ]
},
{
  "_id": "63bf7ccef0323974200016b1",
  "amount": "$145.16",
  "buyer": "Delores Collabine",
  "productIds": [
      "63bf7ac9f0323975d6001694",
      "63bf7ac9f03239966c001697",
      "63bf7ac9f032394cbd00169a",
      "63bf7ac9f03239eb9d0016c8",
      "63bf7ac9f0323975d6001696"
  ]
},
{
  "_id": "63bf7ccef0323974200016b2",
  "amount": "$90.37",
  "buyer": "Anstice Bagge",
  "productIds": [
      "63bf7ac9f03239343e00169c",
      "63bf7ac9f03239966c001693",
      "63bf7ac9f03239f92000168b",
      "63bf7ac9f03239eb9d0016c5",
      "63bf7ac9f03239eb9d0016c4"
  ]
},
{
  "_id": "63bf7ccef0323974200016b3",
  "amount": "$202.24",
  "buyer": "Tamar Hefferan",
  "productIds": [
      "63bf7ac9f03239554c00244a",
      "63bf7ac9f0323901e6001554",
      "63bf7ac9f032394f5f002436",
      "63bf7ac9f03239f92000168e"
  ]
},
{
  "_id": "63bf7ccef0323974200016b4",
  "amount": "$206.71",
  "buyer": "Patience Bricket",
  "productIds": [
      "63bf7ac9f032394f5f002437",
      "63bf7ac9f03239343e00169d",
      "63bf7ac9f032396a8e001692",
      "63bf7ac9f032397b4f0015fe",
      "63bf7ac9f032397420001699"
  ]
},
{
  "_id": "63bf7ccef0323974200016b5",
  "amount": "$169.41",
  "buyer": "Jennilee Croucher",
  "productIds": [
      "63bf7ac9f03239554c00244b",
      "63bf7ac9f0323901e6001556",
      "63bf7ac9f032394cbd00169e",
      "63bf7ac9f0323937a5001688",
      "63bf7ac9f032394f5f002435"
  ]
},
{
  "_id": "63bf7ccef0323974200016b6",
  "amount": "$244.79",
  "buyer": "Gordie Russon",
  "productIds": [
      "63bf7ac9f032396a8e001693",
      "63bf7ac9f0323975d6001695",
      "63bf7ac9f0323901e6001552",
      "63bf7ac9f03239eb9d0016c6"
  ]
},
{
  "_id": "63bf7ccef0323974200016b7",
  "amount": "$195.80",
  "buyer": "Freddy Siaskowski",
  "productIds": [
      "63bf7ac9f0323922d2001690",
      "63bf7ac9f032396a8e001691",
      "63bf7ac9f03239eb9d0016cc",
      "63bf7ac9f032397b4f0015fd"
  ]
},
{
  "_id": "63bf7ccef0323974200016b8",
  "amount": "$179.68",
  "buyer": "Jeremias Frusher",
  "productIds": [
      "63bf7ac9f03239f92000168a",
      "63bf7ac9f032397420001698",
      "63bf7ac9f03239aec9001560",
      "63bf7ac9f0323937a500168a"
  ]
},
{
  "_id": "63bf7ccef0323974200016b9",
  "amount": "$38.52",
  "buyer": "Rodolphe Booley",
  "productIds": [
      "63bf7ac9f032394f5f002437",
      "63bf7ac9f03239343e00169c",
      "63bf7ac9f0323922d2001692"
  ]
},
{
  "_id": "63bf7ccef0323974200016ba",
  "amount": "$92.76",
  "buyer": "Nedi Lagadu",
  "productIds": [
      "63bf7ac9f03239aec9001562",
      "63bf7ac9f032396a8e001690",
      "63bf7ac9f03239aec9001561",
      "63bf7ac9f032394f5f002436"
  ]
},
{
  "_id": "63bf7ccef0323974200016bb",
  "amount": "$70.66",
  "buyer": "Lotty Heinlein",
  "productIds": [
      "63bf7ac9f03239554c00244c",
      "63bf7ac9f0323975d6001696",
      "63bf7ac9f032394f5f002433",
      "63bf7ac9f032395ccf00168e"
  ]
},
{
  "_id": "63bf7ccef0323974200016bc",
  "amount": "$270.21",
  "buyer": "Josefina Flacke",
  "productIds": [
      "63bf7ac9f03239f92000168d",
      "63bf7ac9f03239aec9001562",
      "63bf7ac9f0323974200016a0",
      "63bf7ac9f032394f5f002436"
  ]
},
{
  "_id": "63bf7ccef0323974200016bd",
  "amount": "$136.99",
  "buyer": "Lorettalorna Napper",
  "productIds": [
      "63bf7ac9f03239aec900155e",
      "63bf7ac9f0323975d6001695",
      "63bf7ac9f03239eb9d0016cc",
      "63bf7ac9f03239aec900155f"
  ]
},
{
  "_id": "63bf7ccef0323974200016be",
  "amount": "$130.97",
  "buyer": "Darelle Gaunt",
  "productIds": [
      "63bf7ac9f032396a8e001691",
      "63bf7ac9f0323901e6001554",
      "63bf7ac9f032394f5f002437",
      "63bf7ac9f0323901e6001556"
  ]
},
{
  "_id": "63bf7ccef0323974200016bf",
  "amount": "$168.49",
  "buyer": "Tani Lathleiffure",
  "productIds": [
      "63bf7ac9f032396d8900000c",
      "63bf7ac9f032394cbd00169c",
      "63bf7ac9f0323937a5001689",
      "63bf7ac9f032394cbd00169a"
  ]
},
{
  "_id": "63bf7ccef0323974200016c0",
  "amount": "$186.02",
  "buyer": "Averil Bagnal",
  "productIds": [
      "63bf7ac9f03239742000169c",
      "63bf7ac9f03239742000169e",
      "63bf7ac9f0323937a5001688",
      "63bf7ac9f032396a8e001690"
  ]
},
{
  "_id": "63bf7ccef0323974200016c1",
  "amount": "$14.24",
  "buyer": "Reinaldos Scorah",
  "productIds": [
      "63bf7ac9f03239554c00244d",
      "63bf7ac9f032394cbd00169e",
      "63bf7ac9f03239f920001689"
  ]
},
{
  "_id": "63bf7ccef0323974200016c2",
  "amount": "$275.91",
  "buyer": "Christa Farrier",
  "productIds": [
      "63bf7ac9f03239742000169e",
      "63bf7ac9f032394f5f002435",
      "63bf7ac9f0323937a500168b",
      "63bf7ac9f032396a8e001690"
  ]
},
{
  "_id": "63bf7ccef0323974200016c3",
  "amount": "$182.83",
  "buyer": "Dorena Spilling",
  "productIds": [
      "63bf7ac9f0323975d6001696",
      "63bf7ac9f03239f92000168a",
      "63bf7ac9f032394cbd00169a",
      "63bf7ac9f03239aec9001555",
      "63bf7ac9f03239eb9d0016c6"
  ]
},
{
  "_id": "63bf7ccef0323974200016c4",
  "amount": "$102.72",
  "buyer": "Glen Brou",
  "productIds": [
      "63bf7ac9f032396a8e001690",
      "63bf7ac9f032395ccf001691",
      "63bf7ac9f0323974200016a0",
      "63bf7ac9f032397b4f0015fc",
      "63bf7ac9f0323975d6001694"
  ]
},
{
  "_id": "63bf7ccef0323974200016c5",
  "amount": "$15.57",
  "buyer": "Edwina Keir",
  "productIds": [
      "63bf7ac9f0323922d2001692",
      "63bf7ac9f03239eb9d0016cc",
      "63bf7ac9f0323975d6001697",
      "63bf7ac9f03239eb9d0016c3",
      "63bf7ac9f03239eb9d0016c4"
  ]
},
{
  "_id": "63bf7ccef0323974200016c6",
  "amount": "$119.90",
  "buyer": "Marcos Coldrick",
  "productIds": [
      "63bf7ac9f032396d8900000a",
      "63bf7ac9f03239966c001692",
      "63bf7ac9f032394f5f002435",
      "63bf7ac9f032396d89000009"
  ]
},
{
  "_id": "63bf7ccef0323974200016c7",
  "amount": "$201.36",
  "buyer": "Lea MacKeague",
  "productIds": [
      "63bf7ac9f0323922d2001691",
      "63bf7ac9f032394cbd00169c",
      "63bf7ac9f032397b4f0015fe",
      "63bf7ac9f0323975d6001696",
      "63bf7ac9f032394f5f002438"
  ]
},
{
  "_id": "63bf7ccef0323974200016c8",
  "amount": "$14.84",
  "buyer": "Leilah Blazewicz",
  "productIds": [
      "63bf7ac9f032397b4f0015fe",
      "63bf7ac9f03239eb9d0016c4",
      "63bf7ac9f032394f5f002438"
  ]
},
{
  "_id": "63bf7ccef0323974200016c9",
  "amount": "$256.63",
  "buyer": "Ritchie Pavlov",
  "productIds": [
      "63bf7ac9f0323922d2001691",
      "63bf7ac9f032397b4f0015fc",
      "63bf7ac9f03239aec9001559",
      "63bf7ac9f032394f5f002434",
      "63bf7ac9f032397b4f0015fd"
  ]
},
{
  "_id": "63bf7ccef0323974200016ca",
  "amount": "$122.80",
  "buyer": "Bertha Loffhead",
  "productIds": [
      "63bf7ac9f03239554c002448",
      "63bf7ac9f03239742000169e",
      "63bf7ac9f0323975d6001694",
      "63bf7ac9f0323937a5001688",
      "63bf7ac9f03239f92000168e"
  ]
},
{
  "_id": "63bf7ccef0323974200016cb",
  "amount": "$212.62",
  "buyer": "Luci Aysik",
  "productIds": [
      "63bf7ac9f032394cbd001699",
      "63bf7ac9f0323975d6001695",
      "63bf7ac9f03239966c001697",
      "63bf7ac9f032394f5f002437",
      "63bf7ac9f0323975d6001697"
  ]
},
{
  "_id": "63bf7ccef0323974200016cc",
  "amount": "$56.90",
  "buyer": "Lesley MacGillacolm",
  "productIds": [
      "63bf7ac9f0323922d2001692",
      "63bf7ac9f0323975d6001694",
      "63bf7ac9f032394f5f002434",
      "63bf7ac9f03239966c001693",
      "63bf7ac9f032396a8e001691"
  ]
},
{
  "_id": "63bf7ccef0323974200016cd",
  "amount": "$118.14",
  "buyer": "Vladamir Lovie",
  "productIds": [
      "63bf7ac9f03239742000169d",
      "63bf7ac9f03239aec9001558",
      "63bf7ac9f03239f92000168a",
      "63bf7ac9f032394cbd001699",
      "63bf7ac9f032397b4f0015fc"
  ]
},
{
  "_id": "63bf7ccef0323974200016ce",
  "amount": "$223.03",
  "buyer": "Luca Argent",
  "productIds": [
      "63bf7ac9f0323975d6001697",
      "63bf7ac9f03239742000169b",
      "63bf7ac9f032395ccf00168f",
      "63bf7ac9f032397420001698",
      "63bf7ac9f03239aec900155b"
  ]
},
{
  "_id": "63bf7ccef0323974200016cf",
  "amount": "$252.07",
  "buyer": "Joycelin Kirman",
  "productIds": [
      "63bf7ac9f03239742000169c",
      "63bf7ac9f032397b4f0015fe",
      "63bf7ac9f032394cbd00169a",
      "63bf7ac9f03239966c001692",
      "63bf7ac9f0323975d6001697"
  ]
},
{
  "_id": "63bf7ccef0323974200016d0",
  "amount": "$188.16",
  "buyer": "Tye Capron",
  "productIds": [
      "63bf7ac9f03239554c00244e",
      "63bf7ac9f03239f92000168d",
      "63bf7ac9f032397b4f0015fd",
      "63bf7ac9f0323937a5001689",
      "63bf7ac9f032394cbd00169c"
  ]
},
{
  "_id": "63bf7ccef0323974200016d1",
  "amount": "$217.54",
  "buyer": "Demetri Gorst",
  "productIds": [
      "63bf7ac9f032394f5f002433",
      "63bf7ac9f032394f5f002437",
      "63bf7ac9f03239aec900155a",
      "63bf7ac9f03239742000169a",
      "63bf7ac9f03239966c001692"
  ]
},
{
  "_id": "63bf7ccef0323974200016d2",
  "amount": "$248.32",
  "buyer": "Jorey Byk",
  "productIds": [
      "63bf7ac9f03239554c00244f",
      "63bf7ac9f0323901e6001552",
      "63bf7ac9f032397420001698",
      "63bf7ac9f03239966c001693",
      "63bf7ac9f032396a8e001692"
  ]
},
{
  "_id": "63bf7ccef0323974200016d3",
  "amount": "$287.76",
  "buyer": "Pandora Monnoyer",
  "productIds": [
      "63bf7ac9f03239aec9001556",
      "63bf7ac9f032394cbd00169c",
      "63bf7ac9f03239f92000168a",
      "63bf7ac9f03239966c001697",
      "63bf7ac9f032394cbd0016a9"
  ]
},
{
  "_id": "63bf7ccef0323974200016d4",
  "amount": "$38.11",
  "buyer": "Cassie Toppas",
  "productIds": [
      "63bf7ac9f03239eb9d0016c3",
      "63bf7ac9f0323975d6001696",
      "63bf7ac9f032394f5f002438",
      "63bf7ac9f032394f5f002435",
      "63bf7ac9f03239f92000168e"
  ]
},
{
  "_id": "63bf7ccef0323974200016d5",
  "amount": "$51.05",
  "buyer": "Jamison Kinloch",
  "productIds": [
      "63bf7ac9f0323974200016a0",
      "63bf7ac9f03239aec9001560",
      "63bf7ac9f032394f5f002434",
      "63bf7ac9f03239742000169d",
      "63bf7ac9f032397b4f0015fc"
  ]
},
{
  "_id": "63bf7ccef0323974200016d6",
  "amount": "$267.65",
  "buyer": "Bald Schreiner",
  "productIds": [
      "63bf7ac9f0323922d2001690",
      "63bf7ac9f032394f5f002434",
      "63bf7ac9f032394cbd001699",
      "63bf7ac9f032396a8e001690",
      "63bf7ac9f032395ccf001691"
  ]
},
{
  "_id": "63bf7ccef0323974200016d7",
  "amount": "$164.82",
  "buyer": "Richardo Hrycek",
  "productIds": [
      "63bf7ac9f03239554c002449",
      "63bf7ac9f032395ccf00168f",
      "63bf7ac9f03239742000168b",
      "63bf7ac9f032394cbd00169c",
      "63bf7ac9f0323975d6001697"
  ]
},
{
  "_id": "63bf7ccef0323974200016d8",
  "amount": "$274.02",
  "buyer": "Holly Saggs",
  "productIds": [
      "63bf7ac9f0323975d6001696",
      "63bf7ac9f032396a8e001693",
      "63bf7ac9f032397b4f0015fe",
      "63bf7ac9f032394cbd001699",
      "63bf7ac9f03239eb9d0016cc"
  ]
},
{
  "_id": "63bf7ccef0323974200016d9",
  "amount": "$113.98",
  "buyer": "Eduard Goulbourne",
  "productIds": [
      "63bf7ac9f03239554c002447",
      "63bf7ac9f032394f5f002436",
      "63bf7ac9f032394f5f002433",
      "63bf7ac9f03239343e00169d"
  ]
},
{
  "_id": "63bf7ccef0323974200016da",
  "amount": "$277.02",
  "buyer": "Lorine Pauls",
  "productIds": [
      "63bf7ac9f03239742000169e",
      "63bf7ac9f03239aec9001558",
      "63bf7ac9f032397420001698",
      "63bf7ac9f032397b4f0015fc",
      "63bf7ac9f032394f5f002433"
  ]
},
{
  "_id": "63bf7ccef0323974200016db",
  "amount": "$55.48",
  "buyer": "Gladys Whiterod",
  "productIds": [
      "63bf7ac9f032397420001698",
      "63bf7ac9f0323975d6001694",
      "63bf7ac9f032394f5f002437",
      "63bf7ac9f032397b4f0015fd",
      "63bf7ac9f0323975d6001696"
  ]
},
{
  "_id": "63bf7ccef0323974200016dc",
  "amount": "$163.74",
  "buyer": "Nert Arnull",
  "productIds": [
      "63bf7ac9f0323975d6001697",
      "63bf7ac9f032394f5f002433",
      "63bf7ac9f03239966c001697",
      "63bf7ac9f03239966c001697",
      "63bf7ac9f032394f5f002435"
  ]
},
{
  "_id": "63bf7ccef0323974200016dd",
  "amount": "$29.18",
  "buyer": "Meryl McKinless",
  "productIds": [
      "63bf7ac9f03239f92000168d",
      "63bf7ac9f03239554c00244b",
      "63bf7ac9f032394f5f002434",
      "63bf7ac9f032396a8e001692",
      "63bf7ac9f03239966c001692"
  ]
},
{
  "_id": "63bf7ccef0323974200016de",
  "amount": "$182.04",
  "buyer": "Madlin Schoffel",
  "productIds": [
      "63bf7ac9f0323922d2001691",
  "63bf7ac9f032394cbd00169a",
  "63bf7ac9f03239f92000168d",
  "63bf7ac9f032395ccf00168f",
  "63bf7ac9f03239742000168a"
  ]
},
{
  "_id": "63bf7ccef0323974200016a6",
  "amount": "$125.85",
  "buyer": "Florian Brookbank",
  "productIds": ["63bf7ac9f0323975d6001693", "63bf7ac9f032396a8e001692"]
},
{
  "_id": "63bf7ccef0323974200016a7",
  "amount": "$264.64",
  "buyer": "Aylmer Klimentyev",
  "productIds": ["63bf7ac9f03239e002001604"]
},
{
  "_id": "63bf7ccef03239966c001698",
  "amount": "$274.87",
  "buyer": "Sancho Sleaford",
  "productIds": [
    "63bf7ac9f0323975d6001694",
    "63bf7ac9f032397b4f0015fe",
    "63bf7ac9f0323922d200168f",
    "63bf7ac9f03239eb9d0016c5"
  ]
},
{
  "_id": "63bf7ccef03239966c001699",
  "amount": "$220.00",
  "buyer": "Evelin Oneile",
  "productIds": [
    "63bf7ac9f032394f5f002433",
    "63bf7ac9f0323937a500168c",
    "63bf7ac9f032396a8e001692"
  ]
},
{
  "_id": "63bf7ccef03239966c00169a",
  "amount": "$277.71",
  "buyer": "Larine Couvet",
  "productIds": ["63bf7ac9f03239966c001692"]
},
{
  "_id": "63bf7ccef03239966c00169b",
  "amount": "$134.74",
  "buyer": "Leonanie Juliff",
  "productIds": ["63bf7ac9f03239aec9001553"]
},
{
  "_id": "63bf7ccef03239966c00169c",
  "amount": "$266.52",
  "buyer": "Aubine Giacomucci",
  "productIds": [
    "63bf7ac9f03239554c002443",
    "63bf7ac9f032397420001697",
    "63bf7ac9f0323937a5001687",
    "63bf7ac9f03239eb9d0016c9"
  ]
},
{
  "_id": "63bf7ccef03239966c00169d",
  "amount": "$142.48",
  "buyer": "Obed Garm",
  "productIds": [
    "63bf7ac9f0323901e6001556",
    "63bf7ac9f032396a8e001693",
    "63bf7ac9f03239eb9d0016c4",
    "63bf7ac9f032396d89000009"
  ]
},
{
  "_id": "63bf7ccef03239966c00169e",
  "amount": "$59.95",
  "buyer": "Arie Yardy",
  "productIds": [
    "63bf7ac9f03239aec9001556",
    "63bf7ac9f032395ccf001690",
    "63bf7ac9f032396d89000007",
    "63bf7ac9f03239855d001553",
    "63bf7ac9f03239554c002448"
  ]
},
{
  "_id": "63bf7ccef03239966c00169f",
  "amount": "$282.21",
  "buyer": "Peter Gallager",
  "productIds": [
    "63bf7ac9f03239f920001689",
    "63bf7ac9f032397b4f0015fb",
    "63bf7ac9f03239554c002446",
    "63bf7ac9f0323922d2001692"
  ]
},
{
  "_id": "63bf7ccef03239966c0016a0",
  "amount": "$59.31",
  "buyer": "Freemon Hargey",
  "productIds": [
    "63bf7ac9f03239cf1b00169b",
    "63bf7ac9f032396d8900000b",
    "63bf7ac9f03239554c002445",
    "63bf7ac9f03239554c002447",
    "63bf7ac9f03239855d001554"
  ]
},
{
  "_id": "63bf7ccef03239966c0016a1",
  "amount": "$202.58",
  "buyer": "Libby Dannett",
  "productIds": [
    "63bf7ac9f0323975d6001695",
    "63bf7ac9f03239aec9001554",
    "63bf7ac9f03239554c002444"
  ]
},
{
  "_id": "63bf7ccef03239966c0016a2",
  "amount": "$106.57",
  "buyer": "Claudetta Kinnett",
  "productIds": ["63bf7ac9f0323975d6001697"]
},
{
  "_id": "63bf7ccef03239966c0016a3",
  "amount": "$292.34",
  "buyer": "Taryn Shankland",
  "productIds": ["63bf7ac9f03239742000169b", "63bf7ac9f032397b4f0015fc"]
},
{
  "_id": "63bf7ccef0323975d6001698",
  "amount": "$178.53",
  "buyer": "Roxanne Impson",
  "productIds": ["63bf7ac9f03239cf1b00169b", "63bf7ac9f032394cbd001699"]
},
{
  "_id": "63bf7ccef0323975d6001699",
  "amount": "$262.23",
  "buyer": "Vyky Rumbelow",
  "productIds": [
    "63bf7ac9f03239aec9001555",
    "63bf7ac9f032394f5f002437",
    "63bf7ac9f0323975d6001694",
    "63bf7ac9f03239e002001605",
    "63bf7ac9f03239cf1b00169d"
  ]
},
{
  "_id": "63bf7ccef0323975d600169a",
  "amount": "$91.65",
  "buyer": "Ethelred Layne",
  "productIds": ["63bf7ac9f032394cbd00169d", "63bf7ac9f032394f5f002436"]
},
{
  "_id": "63bf7ccef0323975d600169b",
  "amount": "$127.72",
  "buyer": "Sigismund Coombes",
  "productIds": [
    "63bf7ac9f0323922d2001693",
    "63bf7ac9f03239eb9d0016c9",
    "63bf7ac9f032397b4f0015fb"
  ]
},
{
  "_id": "63bf7ccef0323975d600169c",
  "amount": "$32.05",
  "buyer": "Lacey Clemanceau",
  "productIds": ["63bf7ac9f03239855d001556", "63bf7ac9f032397b4f001600"]
},
{
  "_id": "63bf7ccef0323975d600169d",
  "amount": "$130.53",
  "buyer": "Monroe Matthewson",
  "productIds": ["63bf7ac9f0323922d2001690", "63bf7ac9f0323937a5001687"]
},
{
  "_id": "63bf7ccef0323975d600169e",
  "amount": "$82.41",
  "buyer": "Martita Kinze",
  "productIds": [
    "63bf7ac9f032397420001699",
    "63bf7ac9f032395ccf001693",
    "63bf7ac9f03239e002001600"
  ]
},
{
  "_id": "63bf7ccef0323975d600169f",
  "amount": "$242.59",
  "buyer": "Suzette Tonkes",
  "productIds": ["63bf7ac9f03239aec9001551"]
},
{
  "_id": "63bf7ccef0323975d60016a0",
  "amount": "$282.57",
  "buyer": "Clare Torns",
  "productIds": ["63bf7ac9f03239eb9d0016c6"]
},
{
  "_id": "63bf7ccef0323975d60016a1",
  "amount": "$193.44",
  "buyer": "Silvia Harrap",
  "productIds": ["63bf7ac9f03239cf1b00169a", "63bf7ac9f03239e002001602"]
},
{
  "_id": "63bf7ccef0323975d60016a2",
  "amount": "$41.09",
  "buyer": "Megen Manicomb",
  "productIds": [
    "63bf7ac9f03239742000169a",
    "63bf7ac9f0323975d6001695",
    "63bf7ac9f03239f92000168a",
    "63bf7ac9f03239855d001554",
    "63bf7ac9f03239554c002445"
  ]
},
{
  "_id": "63bf7ccef0323975d60016a3",
  "amount": "$167.97",
  "buyer": "Lacee Dyche",
  "productIds": [
    "63bf7ac9f03239aec9001554",
    "63bf7ac9f032395ccf001691",
    "63bf7ac9f03239742000169b"
  ]
},
{
  "_id": "63bf7ccef032396a8e001694",
  "amount": "$89.43",
  "buyer": "Ravi Morrant",
  "productIds": ["63bf7ac9f032397b4f0015fb"]
},
{
  "_id": "63bf7ccef032396a8e001695",
  "amount": "$185.00",
  "buyer": "Ida Rolles",
  "productIds": ["63bf7ac9f032397b4f001600", "63bf7ac9f032397420001698"]
},
{
  "_id": "63bf7ccef032396a8e001696",
  "amount": "$58.82",
  "buyer": "Melicent Tembridge",
  "productIds": ["63bf7ac9f0323937a500168a"]
},
{
  "_id": "63bf7ccef032396a8e001697",
  "amount": "$57.02",
  "buyer": "Gerald Egell",
  "productIds": [
    "63bf7ac9f03239cf1b001698",
    "63bf7ac9f03239343e00169c",
    "63bf7ac9f0323975d6001694",
    "63bf7ac9f032397b4f0015ff"
  ]
},
{
  "_id": "63bf7ccef032396a8e001698",
  "amount": "$78.59",
  "buyer": "Lorelei Siebart",
  "productIds": [
    "63bf7ac9f0323975d6001697",
    "63bf7ac9f0323901e6001555",
    "63bf7ac9f032394f5f002433",
    "63bf7ac9f03239aec9001555",
    "63bf7ac9f032394f5f002437"
  ]
},
{
  "_id": "63bf7ccef032396a8e001699",
  "amount": "$297.89",
  "buyer": "Cullie Lampens",
  "productIds": [
    "63bf7ac9f032396a8e001691",
    "63bf7ac9f032394cbd00169d",
    "63bf7ac9f03239855d001556",
    "63bf7ac9f0323901e6001554",
    "63bf7ac9f032395ccf001690"
  ]
},
{
  "_id": "63bf7ccef032396a8e00169a",
  "amount": "$242.06",
  "buyer": "Cora Pasque",
  "productIds": [
    "63bf7ac9f03239343e00169f",
    "63bf7ac9f032396d8900000b",
    "63bf7ac9f03239aec9001554",
    "63bf7ac9f032394f5f002436"
  ]
},
{
  "_id": "63bf7ccef032396a8e00169b",
  "amount": "$26.01",
  "buyer": "Lou Singyard",
  "productIds": [
    "63bf7ac9f0323901e6001552",
    "63bf7ac9f0323975d6001693",
    "63bf7ac9f032394f5f002434"
  ]
},
{
  "_id": "63bf7ccef032396a8e00169c",
  "amount": "$123.88",
  "buyer": "Patsy Cargill",
  "productIds": [
    "63bf7ac9f032394cbd001699",
    "63bf7ac9f03239eb9d0016ca",
    "63bf7ac9f032396d8900000a",
    "63bf7ac9f03239554c002445"
  ]
},
{
  "_id": "63bf7ccef032396a8e00169d",
  "amount": "$221.16",
  "buyer": "Naoma Abrams",
  "productIds": [
    "63bf7ac9f03239742000169b",
    "63bf7ac9f03239554c002446",
    "63bf7ac9f03239cf1b00169d"
  ]
},
{
  "_id": "63bf7ccef032396a8e00169e",
  "amount": "$55.67",
  "buyer": "Susann Dri",
  "productIds": [
    "63bf7ac9f032394cbd00169a",
    "63bf7ac9f03239eb9d0016c6",
    "63bf7ac9f032396d89000007"
  ]
},
{
  "_id": "63bf7ccef032396a8e00169f",
  "amount": "$79.87",
  "buyer": "Billye Durward",
  "productIds": [
    "63bf7ac9f032397b4f0015fc",
    "63bf7ac9f03239eb9d0016c9",
    "63bf7ac9f0323975d6001692",
    "63bf7ac9f03239e002001602",
    "63bf7ac9f03239f92000168e"
  ]
},
{
  "_id": "63bf7ccef032395ccf001694",
  "amount": "$216.01",
  "buyer": "Thadeus Meredith",
  "productIds": [
    "63bf7ac9f03239f92000168a",
    "63bf7ac9f032394f5f002433",
    "63bf7ac9f03239eb9d0016c8",
    "63bf7ac9f032396d8900000a"
  ]
},
{
  "_id": "63bf7ccef032395ccf001695",
  "amount": "$69.63",
  "buyer": "Isiahi MacMorland",
  "productIds": [
    "63bf7ac9f03239f92000168d",
    "63bf7ac9f032396a8e001693"
  ]
},
{
  "_id": "63bf7ccef032395ccf001696",
  "amount": "$204.00",
  "buyer": "Jaquelin Thomson",
  "productIds": [
    "63bf7ac9f03239aec9001554",
    "63bf7ac9f03239aec9001555",
    "63bf7ac9f0323937a500168b",
    "63bf7ac9f032396a8e001690",
    "63bf7ac9f03239e002001602"
  ]
},
{
  "_id": "63bf7ccef032395ccf001697",
  "amount": "$283.84",
  "buyer": "Page Quiney",
  "productIds": [
    "63bf7ac9f03239eb9d0016c4",
    "63bf7ac9f03239aec9001552",
    "63bf7ac9f03239cf1b00169b"
  ]
},
{
  "_id": "63bf7ccef032395ccf001698",
  "amount": "$32.76",
  "buyer": "Stephana Bulcroft",
  "productIds": [
    "63bf7ac9f03239742000169a",
    "63bf7ac9f032397b4f0015fc",
    "63bf7ac9f03239554c002447",
    "63bf7ac9f0323922d200168e",
    "63bf7ac9f0323937a500168c"
  ]
},
{
  "_id": "63bf7ccef032395ccf001699",
  "amount": "$34.52",
  "buyer": "Desdemona Zukierman",
  "productIds": [
    "63bf7ac9f032396d8900000c",
    "63bf7ac9f032397b4f0015fd",
    "63bf7ac9f032394f5f002438",
    "63bf7ac9f0323975d6001696",
    "63bf7ac9f03239343e00169c"
  ]
},
{
  "_id": "63bf7ccef032395ccf00169a",
  "amount": "$248.19",
  "buyer": "Fredericka Ayliffe",
  "productIds": [
    "63bf7ac9f032397420001696",
    "63bf7ac9f03239eb9d0016ca",
    "63bf7ac9f032395ccf001690",
    "63bf7ac9f03239e002001600"
  ]
},
{
  "_id": "63bf7ccef032395ccf00169b",
  "amount": "$115.61",
  "buyer": "Rouvin Breit",
  "productIds": [
    "63bf7ac9f03239e002001601",
    "63bf7ac9f03239966c001695",
    "63bf7ac9f032394cbd00169e",
    "63bf7ac9f032394f5f002436"
  ]
},
{
  "_id": "63bf7ccef032395ccf00169c",
  "amount": "$158.54",
  "buyer": "Marlyn Packington",
  "productIds": [
    "63bf7ac9f03239cf1b00169d",
    "63bf7ac9f032394f5f002434",
    "63bf7ac9f03239f92000168b",
    "63bf7ac9f032396a8e00168f"
  ]
},
{
  "_id": "63bf7ccef032395ccf00169d",
  "amount": "$189.62",
  "buyer": "Ric Heasly",
  "productIds": [
    "63bf7ac9f032395ccf001692",
    "63bf7ac9f03239eb9d0016cb"
  ]
},
{
  "_id": "63bf7ccef032395ccf00169e",
  "amount": "$215.68",
  "buyer": "Rhoda Furst",
  "productIds": [
    "63bf7ac9f03239aec9001551"
  ]
},
{
  "_id": "63bf7ccef032395ccf00169f",
  "amount": "$264.99",
  "buyer": "Khalil Climpson",
  "productIds": [
    "63bf7ac9f0323922d2001690"
  ]
},
{
  "_id": "63bf7ccef032397b4f001601",
  "amount": "$218.65",
  "buyer": "Padgett Brimelow",
  "productIds": [
    "63bf7ac9f0323901e6001552",
    "63bf7ac9f03239eb9d0016c6",
    "63bf7ac9f0323922d2001692",
    "63bf7ac9f03239f92000168b",
    "63bf7ac9f03239aec9001553"
  ]
},
  {
    "_id": "63bf7ccef03239f920001695",
    "amount": "$253.84",
    "buyer": "Nikki Overlow",
    "productIds": [
      "63bf7ac9f03239eb9d0016c5",
      "63bf7ac9f032396d89000007",
      "63bf7ac9f032394cbd001699"
    ]
  },
  {
    "_id": "63bf7ccef03239f920001696",
    "amount": "$150.73",
    "buyer": "Giffard Slesser",
    "productIds": [
      "63bf7ac9f032394f5f002435",
      "63bf7ac9f03239eb9d0016c9",
      "63bf7ac9f032394f5f002438"
    ]
  },
  {
    "_id": "63bf7ccef03239f920001697",
    "amount": "$65.72",
    "buyer": "Gerik Wherton",
    "productIds": [
      "63bf7ac9f03239966c001697",
      "63bf7ac9f032397b4f0015fb",
      "63bf7ac9f032394f5f002433"
    ]
  },
  {
    "_id": "63bf7ccef03239f920001698",
    "amount": "$194.44",
    "buyer": "Hebert Dorrington",
    "productIds": [
      "63bf7ac9f03239cf1b00169c"
    ]
  },
  {
    "_id": "63bf7ccef03239f920001699",
    "amount": "$248.57",
    "buyer": "Mable Stirrup",
    "productIds": [
      "63bf7ac9f03239855d001552",
      "63bf7ac9f032395ccf00168e",
      "63bf7ac9f03239554c002444",
      "63bf7ac9f03239e002001601",
      "63bf7ac9f03239554c002443"
    ]
  },
  {
    "_id": "63bf7ccef03239f92000169a",
    "amount": "$276.83",
    "buyer": "Dorothy Cristofolini",
    "productIds": [
      "63bf7ac9f03239966c001694",
      "63bf7ac9f032396d8900000a",
      "63bf7ac9f03239cf1b001699"
    ]
  },
  {
    "_id": "63bf7ccef032394f5f002439",
    "amount": "$175.44",
    "buyer": "Reuben Davidzon",
    "productIds": [
      "63bf7ac9f03239e002001600"
    ]
  },
  {
    "_id": "63bf7ccef032394f5f00243a",
    "amount": "$141.20",
    "buyer": "Mitchell Scriven",
    "productIds": [
      "63bf7ac9f0323937a500168a",
      "63bf7ac9f03239eb9d0016cb",
      "63bf7ac9f03239966c001692",
      "63bf7ac9f032397420001698",
      "63bf7ac9f03239eb9d0016c8"
    ]
  },
  {
    "_id": "63bf7ccef032394f5f00243b",
    "amount": "$137.00",
    "buyer": "Jozef McFfaden",
    "productIds": [
      "63bf7ac9f032394f5f002438",
      "63bf7ac9f03239855d001555",
      "63bf7ac9f03239855d001556",
      "63bf7ac9f032397b4f0015ff"
    ]
  },
  {
    "_id": "63bf7ccef032394f5f00243c",
    "amount": "$30.46",
    "buyer": "Sarajane Giovannilli",
    "productIds": [
      "63bf7ac9f03239343e00169c"
    ]
  },
  {
    "_id": "63bf7ccef032394f5f00243d",
    "amount": "$163.77",
    "buyer": "Malchy Hanbury-Brown",
    "productIds": [
      "63bf7ac9f03239966c001696"
    ]
  },
  {
    "_id": "63bf7ccef032394f5f00243e",
    "amount": "$272.04",
    "buyer": "Nathanil Aidler",
    "productIds": [
      "63bf7ac9f032397b4f0015fe",
      "63bf7ac9f032394cbd00169c"
    ]
  },
  {
    "_id": "63bf7ccef032394f5f00243f",
    "amount": "$270.05",
    "buyer": "Petronille Ganter",
    "productIds": [
      "63bf7ac9f03239cf1b00169b"
    ]
  },
  {
    "_id": "63bf7ccef032394f5f002440",
    "amount": "$183.86",
    "buyer": "Nanni Bettles",
    "productIds": [
      "63bf7ac9f0323975d6001695",
      "63bf7ac9f032395ccf001690"
    ]
  },
  {
    "_id": "63bf7ccef032394f5f002441",
    "amount": "$13.39",
    "buyer": "Marcello Connechy",
    "productIds": [
      "63bf7ac9f0323922d200168e",
      "63bf7ac9f03239554c002443",
      "63bf7ac9f03239e002001605",
      "63bf7ac9f03239e002001601",
      "63bf7ac9f0323922d200168f"
    ]
  },
  {
    "_id": "63bf7ccef032394f5f002442",
    "amount": "$158.95",
    "buyer": "Reggis Ketton",
    "productIds": [
      "63bf7ac9f03239343e00169d",
      "63bf7ac9f03239343e00169b",
      "63bf7ac9f032395ccf001691",
      "63bf7ac9f03239855d001553"
    ]
  },
  {
    "_id": "63bf7ccef032394f5f002443",
    "amount": "$103.60",
    "buyer": "Willyt Cato",
    "productIds": [
      "63bf7ac9f0323922d2001693"
    ]
  },
  {
    "_id": "63bf7ccef032394f5f002444",
    "amount": "$154.99",
    "buyer": "Ira Martinello",
    "productIds": [
      "63bf7ac9f032395ccf00168e",
      "63bf7ac9f0323901e6001551"
    ]
  },
  {
    "_id": "63bf7ccef0323937a500168d",
    "amount": "$197.90",
    "buyer": "Udall Alessandretti",
    "productIds": [
      "63bf7ac9f032397b4f0015ff",
      "63bf7ac9f03239eb9d0016c3",
      "63bf7ac9f03239eb9d0016c8"
    ]
  },
  {
    "_id": "63bf7ccef0323937a500168e",
    "amount": "$28.26",
    "buyer": "Erminia Giraudo",
    "productIds": [
      "63bf7ac9f03239cf1b00169d",
      "63bf7ac9f032396a8e001692",
      "63bf7ac9f032394cbd00169a",
      "63bf7ac9f03239e002001605"
    ]
  },
  {
    "_id": "63bf7ccef032396d89000015",
    "amount": "$198.46",
    "buyer": "Josselyn Banbrook",
    "productIds": [
      "63bf7ac9f0323922d200168f",
      "63bf7ac9f03239f92000168c",
      "63bf7ac9f032397420001699",
      "63bf7ac9f03239eb9d0016cb"
    ]
  },
  {
    "_id": "63bf7ccef032396d89000016",
    "amount": "$69.69",
    "buyer": "Luigi Cuncliffe",
    "productIds": [
      "63bf7ac9f032397b4f001602",
      "63bf7ac9f032397420001697",
      "63bf7ac9f032394f5f002437",
      "63bf7ac9f032394f5f002433"
    ]
  },
  {
    "_id": "63bf7ccef032396d89000017",
    "amount": "$171.35",
    "buyer": "Reube Withrington",
    "productIds": [
      "63bf7ac9f0323937a500168b",
      "63bf7ac9f032397420001697",
      "63bf7ac9f03239eb9d0016cb"
    ]
  },
  {
    "_id": "63bf7ccef032396d89000018",
    "amount": "$183.09",
    "buyer": "Sarge Boosey",
    "productIds": [
      "63bf7ac9f0323922d200168f",
      "63bf7ac9f03239eb9d0016cd",
      "63bf7ac9f03239eb9d0016c7",
      "63bf7ac9f032396a8e001693",
      "63bf7ac9f032396a8e00168e"
    ]
  },
  {
    "_id": "63bf7ccef032396d89000019",
    "amount": "$204.06",
    "buyer": "Bertine Veque",
    "productIds": [
      "63bf7ac9f03239cf1b001698",
      "63bf7ac9f03239eb9d0016cc",
      "63bf7ac9f032394cbd00169c"
    ]
  },
  {
    "_id": "63bf7ccef032396d8900001a",
    "amount": "$242.09",
    "buyer": "Inge Christofor",
    "productIds": [
      "63bf7ac9f032394f5f002433",
      "63bf7ac9f032397420001698",
      "63bf7ac9f03239f92000168e",
      "63bf7ac9f0323975d6001694",
      "63bf7ac9f03239f92000168d"
    ]
  },
  {
    "_id": "63bf7ccef032396d8900001b",
    "amount": "$265.41",
    "buyer": "Huntlee Kerswill",
    "productIds": [
      "63bf7ac9f0323975d6001692",
      "63bf7ac9f03239cf1b00169c",
      "63bf7ac9f03239966c001696",
      "63bf7ac9f0323922d2001692"
    ]
  },
  {
    "_id": "63bf7ccef032396d8900001c",
    "amount": "$149.58",
    "buyer": "Lemmy Heinig",
    "productIds": [
      "63bf7ac9f03239855d001554",
      "63bf7ac9f032396a8e001691"
    ]
  },
  {
    "_id": "63bf7ccef032396d8900001d",
    "amount": "$189.14",
    "buyer": "Marilin Jandak",
    "productIds": [
      "63bf7ac9f0323901e6001553"
    ]
  },
  {
    "_id": "63bf7ccef032396d8900001e",
    "amount": "$33.22",
    "buyer": "Jorgan Hobbs",
    "productIds": [
      "63bf7ac9f03239855d001556",
      "63bf7ac9f03239eb9d0016c6"
    ]
  },
  {
    "_id": "63bf7ccef032396d8900001f",
    "amount": "$25.39",
    "buyer": "Leontyne Duffield",
    "productIds": [
      "63bf7ac9f032397420001698",
      "63bf7ac9f0323922d200168e",
      "63bf7ac9f03239cf1b001698"
    ]
  },
  {
    "_id": "63bf7ccef032396d89000020",
    "amount": "$216.76",
    "buyer": "Melvin Libri",
    "productIds": [
      "63bf7ac9f032396a8e001690",
      "63bf7ac9f032394f5f002435",
      "63bf7ac9f032394cbd00169d",
      "63bf7ac9f032394f5f002434"
    ]
  },
  {
    "_id": "63bf7ccef032396d89000021",
    "amount": "$226.34",
    "buyer": "Regina Normanvill",
    "productIds": [
      "63bf7ac9f032395ccf001693",
      "63bf7ac9f03239966c001692",
      "63bf7ac9f032397420001699"
    ]
  },
  {
    "_id": "63bf7ccef032396d89000022",
    "amount": "$169.47",
    "buyer": "Darsey McVie",
    "productIds": [
      "63bf7ac9f032397420001699",
      "63bf7ac9f032394cbd00169e",
      "63bf7ac9f0323975d6001693"
    ]
  },
  {
    "_id": "63bf7ccef032396d89000023",
    "amount": "$107.26",
    "buyer": "Bernadine Sircombe",
    "productIds": [
      "63bf7ac9f032397420001699",
      "63bf7ac9f032397420001699",
      "63bf7ac9f032396a8e00168f",
      "63bf7ac9f032397420001699"
    ]
  },
  {
    "_id": "63bf7ccef032396d89000024",
    "amount": "$136.58",
    "buyer": "Theodora Burford",
    "productIds": [
      "63bf7ac9f032397420001699",
      "63bf7ac9f032394f5f002438",
      "63bf7ac9f03239f92000168b",
      "63bf7ac9f032397420001698"
    ]
  }

]
}